{
  "last_updated": "2026-06-05T22:34:15.350332",
  "total_found": 140,
  "below_target": 1,
  "alarms_sent_this_run": 1,
  "direct_threshold_pct": 50,
  "stopover_threshold_pct": 90,
  "data_source": "playwright_chromium",
  "flights": [
    {
      "route": "IST-CDG",
      "origin": "IST",
      "dest": "CDG",
      "depart_date": "2026-09-11",
      "return_date": "2026-09-14",
      "price": 1000.0,
      "airline": "Çeşitli",
      "target": 3000,
      "alarm_threshold": 1500,
      "savings_pct": 67,
      "is_below_target": false,
      "is_mistake_fare": true,
      "has_stopover": true,
      "google_link": "https://www.google.com/travel/flights?hl=tr&curr=TRY&gl=TR&q=IST%20to%20CDG%202026-09-11%202026-09-14",
      "scraped_at": "2026-06-05T22:16:46.591328",
      "data_source": "url_html"
    },
    {
      "route": "IST-CDG",
      "origin": "IST",
      "dest": "CDG",
      "depart_date": "2026-07-31",
      "return_date": "2026-08-03",
      "price": 1000.0,
      "airline": "Çeşitli",
      "target": 3000,
      "alarm_threshold": 1500,
      "savings_pct": 67,
      "is_below_target": false,
      "is_mistake_fare": true,
      "has_stopover": true,
      "google_link": "https://www.google.com/travel/flights?hl=tr&curr=TRY&gl=TR&q=IST%20to%20CDG%202026-07-31%202026-08-03",
      "scraped_at": "2026-06-05T22:17:11.515860",
      "data_source": "url_html"
    },
    {
      "route": "IST-LHR",
      "origin": "IST",
      "dest": "LHR",
      "depart_date": "2026-09-11",
      "return_date": "2026-09-14",
      "price": 1000.0,
      "airline": "Çeşitli",
      "target": 3200,
      "alarm_threshold": 1600,
      "savings_pct": 69,
      "is_below_target": false,
      "is_mistake_fare": true,
      "has_stopover": true,
      "google_link": "https://www.google.com/travel/flights?hl=tr&curr=TRY&gl=TR&q=IST%20to%20LHR%202026-09-11%202026-09-14",
      "scraped_at": "2026-06-05T22:18:05.093432",
      "data_source": "url_html"
    },
    {
      "route": "IST-AMS",
      "origin": "IST",
      "dest": "AMS",
      "depart_date": "2026-07-03",
      "return_date": "2026-07-06",
      "price": 1000.0,
      "airline": "Çeşitli",
      "target": 2800,
      "alarm_threshold": 1400,
      "savings_pct": 64,
      "is_below_target": false,
      "is_mistake_fare": true,
      "has_stopover": true,
      "google_link": "https://www.google.com/travel/flights?hl=tr&curr=TRY&gl=TR&q=IST%20to%20AMS%202026-07-03%202026-07-06",
      "scraped_at": "2026-06-05T22:18:32.128762",
      "data_source": "url_html"
    },
    {
      "route": "IST-AMS",
      "origin": "IST",
      "dest": "AMS",
      "depart_date": "2026-07-17",
      "return_date": "2026-07-20",
      "price": 1000.0,
      "airline": "Çeşitli",
      "target": 2800,
      "alarm_threshold": 1400,
      "savings_pct": 64,
      "is_below_target": false,
      "is_mistake_fare": true,
      "has_stopover": true,
      "google_link": "https://www.google.com/travel/flights?hl=tr&curr=TRY&gl=TR&q=IST%20to%20AMS%202026-07-17%202026-07-20",
      "scraped_at": "2026-06-05T22:19:03.729907",
      "data_source": "url_html"
    },
    {
      "route": "IST-MAD",
      "origin": "IST",
      "dest": "MAD",
      "depart_date": "2026-06-26",
      "return_date": "2026-06-29",
      "price": 1000.0,
      "airline": "Çeşitli",
      "target": 3100,
      "alarm_threshold": 1550,
      "savings_pct": 68,
      "is_below_target": false,
      "is_mistake_fare": true,
      "has_stopover": true,
      "google_link": "https://www.google.com/travel/flights?hl=tr&curr=TRY&gl=TR&q=IST%20to%20MAD%202026-06-26%202026-06-29",
      "scraped_at": "2026-06-05T22:21:16.009849",
      "data_source": "url_html"
    },
    {
      "route": "IST-FRA",
      "origin": "IST",
      "dest": "FRA",
      "depart_date": "2026-07-10",
      "return_date": "2026-07-13",
      "price": 1000.0,
      "airline": "Çeşitli",
      "target": 2700,
      "alarm_threshold": 1350,
      "savings_pct": 63,
      "is_below_target": false,
      "is_mistake_fare": true,
      "has_stopover": true,
      "google_link": "https://www.google.com/travel/flights?hl=tr&curr=TRY&gl=TR&q=IST%20to%20FRA%202026-07-10%202026-07-13",
      "scraped_at": "2026-06-05T22:22:13.750343",
      "data_source": "url_html"
    },
    {
      "route": "IST-FRA",
      "origin": "IST",
      "dest": "FRA",
      "depart_date": "2026-07-17",
      "return_date": "2026-07-20",
      "price": 1000.0,
      "airline": "Çeşitli",
      "target": 2700,
      "alarm_threshold": 1350,
      "savings_pct": 63,
      "is_below_target": false,
      "is_mistake_fare": true,
      "has_stopover": true,
      "google_link": "https://www.google.com/travel/flights?hl=tr&curr=TRY&gl=TR&q=IST%20to%20FRA%202026-07-17%202026-07-20",
      "scraped_at": "2026-06-05T22:22:46.161188",
      "data_source": "url_html"
    },
    {
      "route": "IST-VIE",
      "origin": "IST",
      "dest": "VIE",
      "depart_date": "2026-07-10",
      "return_date": "2026-07-13",
      "price": 1000.0,
      "airline": "Çeşitli",
      "target": 2400,
      "alarm_threshold": 1200,
      "savings_pct": 58,
      "is_below_target": false,
      "is_mistake_fare": true,
      "has_stopover": true,
      "google_link": "https://www.google.com/travel/flights?hl=tr&curr=TRY&gl=TR&q=IST%20to%20VIE%202026-07-10%202026-07-13",
      "scraped_at": "2026-06-05T22:24:17.116813",
      "data_source": "url_html"
    },
    {
      "route": "IST-VIE",
      "origin": "IST",
      "dest": "VIE",
      "depart_date": "2026-08-28",
      "return_date": "2026-08-31",
      "price": 1000.0,
      "airline": "Çeşitli",
      "target": 2400,
      "alarm_threshold": 1200,
      "savings_pct": 58,
      "is_below_target": false,
      "is_mistake_fare": true,
      "has_stopover": true,
      "google_link": "https://www.google.com/travel/flights?hl=tr&curr=TRY&gl=TR&q=IST%20to%20VIE%202026-08-28%202026-08-31",
      "scraped_at": "2026-06-05T22:24:42.574027",
      "data_source": "url_html"
    },
    {
      "route": "IST-DXB",
      "origin": "IST",
      "dest": "DXB",
      "depart_date": "2026-07-10",
      "return_date": "2026-07-13",
      "price": 1000.0,
      "airline": "Çeşitli",
      "target": 2200,
      "alarm_threshold": 1100,
      "savings_pct": 55,
      "is_below_target": false,
      "is_mistake_fare": true,
      "has_stopover": true,
      "google_link": "https://www.google.com/travel/flights?hl=tr&curr=TRY&gl=TR&q=IST%20to%20DXB%202026-07-10%202026-07-13",
      "scraped_at": "2026-06-05T22:26:56.018689",
      "data_source": "url_html"
    },
    {
      "route": "IST-DXB",
      "origin": "IST",
      "dest": "DXB",
      "depart_date": "2026-09-25",
      "return_date": "2026-09-28",
      "price": 1000.0,
      "airline": "Çeşitli",
      "target": 2200,
      "alarm_threshold": 1100,
      "savings_pct": 55,
      "is_below_target": false,
      "is_mistake_fare": true,
      "has_stopover": true,
      "google_link": "https://www.google.com/travel/flights?hl=tr&curr=TRY&gl=TR&q=IST%20to%20DXB%202026-09-25%202026-09-28",
      "scraped_at": "2026-06-05T22:27:23.841687",
      "data_source": "url_html"
    },
    {
      "route": "IST-JFK",
      "origin": "IST",
      "dest": "JFK",
      "depart_date": "2026-09-11",
      "return_date": "2026-09-14",
      "price": 1000.0,
      "airline": "Çeşitli",
      "target": 18000,
      "alarm_threshold": 9000,
      "savings_pct": 94,
      "is_below_target": true,
      "is_mistake_fare": true,
      "has_stopover": true,
      "google_link": "https://www.google.com/travel/flights?hl=tr&curr=TRY&gl=TR&q=IST%20to%20JFK%202026-09-11%202026-09-14",
      "scraped_at": "2026-06-05T22:27:49.356212",
      "data_source": "url_html"
    },
    {
      "route": "SAW-CDG",
      "origin": "SAW",
      "dest": "CDG",
      "depart_date": "2026-07-03",
      "return_date": "2026-07-06",
      "price": 1000.0,
      "airline": "Çeşitli",
      "target": 2800,
      "alarm_threshold": 1400,
      "savings_pct": 64,
      "is_below_target": false,
      "is_mistake_fare": true,
      "has_stopover": true,
      "google_link": "https://www.google.com/travel/flights?hl=tr&curr=TRY&gl=TR&q=SAW%20to%20CDG%202026-07-03%202026-07-06",
      "scraped_at": "2026-06-05T22:29:41.274943",
      "data_source": "url_html"
    },
    {
      "route": "SAW-CDG",
      "origin": "SAW",
      "dest": "CDG",
      "depart_date": "2026-08-14",
      "return_date": "2026-08-17",
      "price": 1000.0,
      "airline": "Çeşitli",
      "target": 2800,
      "alarm_threshold": 1400,
      "savings_pct": 64,
      "is_below_target": false,
      "is_mistake_fare": true,
      "has_stopover": true,
      "google_link": "https://www.google.com/travel/flights?hl=tr&curr=TRY&gl=TR&q=SAW%20to%20CDG%202026-08-14%202026-08-17",
      "scraped_at": "2026-06-05T22:30:13.766325",
      "data_source": "url_html"
    },
    {
      "route": "SAW-LHR",
      "origin": "SAW",
      "dest": "LHR",
      "depart_date": "2026-06-26",
      "return_date": "2026-06-29",
      "price": 1000.0,
      "airline": "Çeşitli",
      "target": 3000,
      "alarm_threshold": 1500,
      "savings_pct": 67,
      "is_below_target": false,
      "is_mistake_fare": true,
      "has_stopover": true,
      "google_link": "https://www.google.com/travel/flights?hl=tr&curr=TRY&gl=TR&q=SAW%20to%20LHR%202026-06-26%202026-06-29",
      "scraped_at": "2026-06-05T22:30:39.196754",
      "data_source": "url_html"
    },
    {
      "route": "SAW-LHR",
      "origin": "SAW",
      "dest": "LHR",
      "depart_date": "2026-07-17",
      "return_date": "2026-07-20",
      "price": 1000.0,
      "airline": "Çeşitli",
      "target": 3000,
      "alarm_threshold": 1500,
      "savings_pct": 67,
      "is_below_target": false,
      "is_mistake_fare": true,
      "has_stopover": true,
      "google_link": "https://www.google.com/travel/flights?hl=tr&curr=TRY&gl=TR&q=SAW%20to%20LHR%202026-07-17%202026-07-20",
      "scraped_at": "2026-06-05T22:31:06.081869",
      "data_source": "url_html"
    },
    {
      "route": "SAW-AMS",
      "origin": "SAW",
      "dest": "AMS",
      "depart_date": "2026-09-11",
      "return_date": "2026-09-14",
      "price": 1000.0,
      "airline": "Çeşitli",
      "target": 2600,
      "alarm_threshold": 1300,
      "savings_pct": 62,
      "is_below_target": false,
      "is_mistake_fare": true,
      "has_stopover": true,
      "google_link": "https://www.google.com/travel/flights?hl=tr&curr=TRY&gl=TR&q=SAW%20to%20AMS%202026-09-11%202026-09-14",
      "scraped_at": "2026-06-05T22:31:35.379387",
      "data_source": "url_html"
    },
    {
      "route": "SAW-BCN",
      "origin": "SAW",
      "dest": "BCN",
      "depart_date": "2026-06-19",
      "return_date": "2026-06-22",
      "price": 1000.0,
      "airline": "Çeşitli",
      "target": 2700,
      "alarm_threshold": 1350,
      "savings_pct": 63,
      "is_below_target": false,
      "is_mistake_fare": true,
      "has_stopover": true,
      "google_link": "https://www.google.com/travel/flights?hl=tr&curr=TRY&gl=TR&q=SAW%20to%20BCN%202026-06-19%202026-06-22",
      "scraped_at": "2026-06-05T22:32:33.188575",
      "data_source": "url_html"
    },
    {
      "route": "SAW-BCN",
      "origin": "SAW",
      "dest": "BCN",
      "depart_date": "2026-09-11",
      "return_date": "2026-09-14",
      "price": 1000.0,
      "airline": "Çeşitli",
      "target": 2700,
      "alarm_threshold": 1350,
      "savings_pct": 63,
      "is_below_target": false,
      "is_mistake_fare": true,
      "has_stopover": true,
      "google_link": "https://www.google.com/travel/flights?hl=tr&curr=TRY&gl=TR&q=SAW%20to%20BCN%202026-09-11%202026-09-14",
      "scraped_at": "2026-06-05T22:33:04.017393",
      "data_source": "url_html"
    },
    {
      "route": "SAW-FCO",
      "origin": "SAW",
      "dest": "FCO",
      "depart_date": "2026-07-10",
      "return_date": "2026-07-13",
      "price": 1000.0,
      "airline": "Çeşitli",
      "target": 2400,
      "alarm_threshold": 1200,
      "savings_pct": 58,
      "is_below_target": false,
      "is_mistake_fare": true,
      "has_stopover": true,
      "google_link": "https://www.google.com/travel/flights?hl=tr&curr=TRY&gl=TR&q=SAW%20to%20FCO%202026-07-10%202026-07-13",
      "scraped_at": "2026-06-05T22:33:31.684890",
      "data_source": "url_html"
    },
    {
      "route": "SAW-FCO",
      "origin": "SAW",
      "dest": "FCO",
      "depart_date": "2026-07-17",
      "return_date": "2026-07-20",
      "price": 1000.0,
      "airline": "Çeşitli",
      "target": 2400,
      "alarm_threshold": 1200,
      "savings_pct": 58,
      "is_below_target": false,
      "is_mistake_fare": true,
      "has_stopover": true,
      "google_link": "https://www.google.com/travel/flights?hl=tr&curr=TRY&gl=TR&q=SAW%20to%20FCO%202026-07-17%202026-07-20",
      "scraped_at": "2026-06-05T22:34:00.335780",
      "data_source": "url_html"
    },
    {
      "route": "IST-VIE",
      "origin": "IST",
      "dest": "VIE",
      "depart_date": "2026-08-28",
      "return_date": "2026-08-31",
      "price": 1010.0,
      "airline": "Çeşitli",
      "target": 2400,
      "alarm_threshold": 1200,
      "savings_pct": 58,
      "is_below_target": false,
      "is_mistake_fare": true,
      "has_stopover": true,
      "google_link": "https://www.google.com/travel/flights?hl=tr&curr=TRY&gl=TR&q=IST%20to%20VIE%202026-08-28%202026-08-31",
      "scraped_at": "2026-06-05T22:24:42.574027",
      "data_source": "url_html"
    },
    {
      "route": "SAW-CDG",
      "origin": "SAW",
      "dest": "CDG",
      "depart_date": "2026-07-03",
      "return_date": "2026-07-06",
      "price": 1090.0,
      "airline": "Çeşitli",
      "target": 2800,
      "alarm_threshold": 1400,
      "savings_pct": 61,
      "is_below_target": false,
      "is_mistake_fare": true,
      "has_stopover": true,
      "google_link": "https://www.google.com/travel/flights?hl=tr&curr=TRY&gl=TR&q=SAW%20to%20CDG%202026-07-03%202026-07-06",
      "scraped_at": "2026-06-05T22:29:41.274943",
      "data_source": "url_html"
    },
    {
      "route": "SAW-CDG",
      "origin": "SAW",
      "dest": "CDG",
      "depart_date": "2026-08-14",
      "return_date": "2026-08-17",
      "price": 1090.0,
      "airline": "Çeşitli",
      "target": 2800,
      "alarm_threshold": 1400,
      "savings_pct": 61,
      "is_below_target": false,
      "is_mistake_fare": true,
      "has_stopover": true,
      "google_link": "https://www.google.com/travel/flights?hl=tr&curr=TRY&gl=TR&q=SAW%20to%20CDG%202026-08-14%202026-08-17",
      "scraped_at": "2026-06-05T22:30:13.766325",
      "data_source": "url_html"
    },
    {
      "route": "SAW-LHR",
      "origin": "SAW",
      "dest": "LHR",
      "depart_date": "2026-07-17",
      "return_date": "2026-07-20",
      "price": 1315.0,
      "airline": "Çeşitli",
      "target": 3000,
      "alarm_threshold": 1500,
      "savings_pct": 56,
      "is_below_target": false,
      "is_mistake_fare": true,
      "has_stopover": true,
      "google_link": "https://www.google.com/travel/flights?hl=tr&curr=TRY&gl=TR&q=SAW%20to%20LHR%202026-07-17%202026-07-20",
      "scraped_at": "2026-06-05T22:31:06.081869",
      "data_source": "url_html"
    },
    {
      "route": "IST-DXB",
      "origin": "IST",
      "dest": "DXB",
      "depart_date": "2026-09-25",
      "return_date": "2026-09-28",
      "price": 1325.0,
      "airline": "Çeşitli",
      "target": 2200,
      "alarm_threshold": 1100,
      "savings_pct": 40,
      "is_below_target": false,
      "is_mistake_fare": true,
      "has_stopover": true,
      "google_link": "https://www.google.com/travel/flights?hl=tr&curr=TRY&gl=TR&q=IST%20to%20DXB%202026-09-25%202026-09-28",
      "scraped_at": "2026-06-05T22:27:23.841687",
      "data_source": "url_html"
    },
    {
      "route": "IST-DXB",
      "origin": "IST",
      "dest": "DXB",
      "depart_date": "2026-09-25",
      "return_date": "2026-09-28",
      "price": 1375.0,
      "airline": "Çeşitli",
      "target": 2200,
      "alarm_threshold": 1100,
      "savings_pct": 38,
      "is_below_target": false,
      "is_mistake_fare": true,
      "has_stopover": true,
      "google_link": "https://www.google.com/travel/flights?hl=tr&curr=TRY&gl=TR&q=IST%20to%20DXB%202026-09-25%202026-09-28",
      "scraped_at": "2026-06-05T22:27:23.841687",
      "data_source": "url_html"
    },
    {
      "route": "SAW-LHR",
      "origin": "SAW",
      "dest": "LHR",
      "depart_date": "2026-06-26",
      "return_date": "2026-06-29",
      "price": 1420.0,
      "airline": "Çeşitli",
      "target": 3000,
      "alarm_threshold": 1500,
      "savings_pct": 53,
      "is_below_target": false,
      "is_mistake_fare": true,
      "has_stopover": true,
      "google_link": "https://www.google.com/travel/flights?hl=tr&curr=TRY&gl=TR&q=SAW%20to%20LHR%202026-06-26%202026-06-29",
      "scraped_at": "2026-06-05T22:30:39.196754",
      "data_source": "url_html"
    },
    {
      "route": "SAW-LHR",
      "origin": "SAW",
      "dest": "LHR",
      "depart_date": "2026-07-17",
      "return_date": "2026-07-20",
      "price": 1420.0,
      "airline": "Çeşitli",
      "target": 3000,
      "alarm_threshold": 1500,
      "savings_pct": 53,
      "is_below_target": false,
      "is_mistake_fare": true,
      "has_stopover": true,
      "google_link": "https://www.google.com/travel/flights?hl=tr&curr=TRY&gl=TR&q=SAW%20to%20LHR%202026-07-17%202026-07-20",
      "scraped_at": "2026-06-05T22:31:06.081869",
      "data_source": "url_html"
    },
    {
      "route": "SAW-FCO",
      "origin": "SAW",
      "dest": "FCO",
      "depart_date": "2026-07-17",
      "return_date": "2026-07-20",
      "price": 1585.0,
      "airline": "Çeşitli",
      "target": 2400,
      "alarm_threshold": 1200,
      "savings_pct": 34,
      "is_below_target": false,
      "is_mistake_fare": true,
      "has_stopover": true,
      "google_link": "https://www.google.com/travel/flights?hl=tr&curr=TRY&gl=TR&q=SAW%20to%20FCO%202026-07-17%202026-07-20",
      "scraped_at": "2026-06-05T22:34:00.335780",
      "data_source": "url_html"
    },
    {
      "route": "SAW-LHR",
      "origin": "SAW",
      "dest": "LHR",
      "depart_date": "2026-06-26",
      "return_date": "2026-06-29",
      "price": 1595.0,
      "airline": "Çeşitli",
      "target": 3000,
      "alarm_threshold": 1500,
      "savings_pct": 47,
      "is_below_target": false,
      "is_mistake_fare": true,
      "has_stopover": true,
      "google_link": "https://www.google.com/travel/flights?hl=tr&curr=TRY&gl=TR&q=SAW%20to%20LHR%202026-06-26%202026-06-29",
      "scraped_at": "2026-06-05T22:30:39.196754",
      "data_source": "url_html"
    },
    {
      "route": "SAW-FCO",
      "origin": "SAW",
      "dest": "FCO",
      "depart_date": "2026-07-17",
      "return_date": "2026-07-20",
      "price": 1675.0,
      "airline": "Çeşitli",
      "target": 2400,
      "alarm_threshold": 1200,
      "savings_pct": 30,
      "is_below_target": false,
      "is_mistake_fare": true,
      "has_stopover": true,
      "google_link": "https://www.google.com/travel/flights?hl=tr&curr=TRY&gl=TR&q=SAW%20to%20FCO%202026-07-17%202026-07-20",
      "scraped_at": "2026-06-05T22:34:00.335780",
      "data_source": "url_html"
    },
    {
      "route": "IST-CDG",
      "origin": "IST",
      "dest": "CDG",
      "depart_date": "2026-09-11",
      "return_date": "2026-09-14",
      "price": 2404.0,
      "airline": "Çeşitli",
      "target": 3000,
      "alarm_threshold": 1500,
      "savings_pct": 20,
      "is_below_target": false,
      "is_mistake_fare": true,
      "has_stopover": true,
      "google_link": "https://www.google.com/travel/flights?hl=tr&curr=TRY&gl=TR&q=IST%20to%20CDG%202026-09-11%202026-09-14",
      "scraped_at": "2026-06-05T22:16:46.591328",
      "data_source": "url_html"
    },
    {
      "route": "IST-LHR",
      "origin": "IST",
      "dest": "LHR",
      "depart_date": "2026-09-11",
      "return_date": "2026-09-14",
      "price": 2404.0,
      "airline": "Çeşitli",
      "target": 3200,
      "alarm_threshold": 1600,
      "savings_pct": 25,
      "is_below_target": false,
      "is_mistake_fare": true,
      "has_stopover": true,
      "google_link": "https://www.google.com/travel/flights?hl=tr&curr=TRY&gl=TR&q=IST%20to%20LHR%202026-09-11%202026-09-14",
      "scraped_at": "2026-06-05T22:18:05.093432",
      "data_source": "url_html"
    },
    {
      "route": "IST-FRA",
      "origin": "IST",
      "dest": "FRA",
      "depart_date": "2026-07-10",
      "return_date": "2026-07-13",
      "price": 2404.0,
      "airline": "Çeşitli",
      "target": 2700,
      "alarm_threshold": 1350,
      "savings_pct": 11,
      "is_below_target": false,
      "is_mistake_fare": true,
      "has_stopover": true,
      "google_link": "https://www.google.com/travel/flights?hl=tr&curr=TRY&gl=TR&q=IST%20to%20FRA%202026-07-10%202026-07-13",
      "scraped_at": "2026-06-05T22:22:13.750343",
      "data_source": "url_html"
    },
    {
      "route": "IST-VIE",
      "origin": "IST",
      "dest": "VIE",
      "depart_date": "2026-07-10",
      "return_date": "2026-07-13",
      "price": 2404.0,
      "airline": "Çeşitli",
      "target": 2400,
      "alarm_threshold": 1200,
      "savings_pct": 0,
      "is_below_target": false,
      "is_mistake_fare": true,
      "has_stopover": true,
      "google_link": "https://www.google.com/travel/flights?hl=tr&curr=TRY&gl=TR&q=IST%20to%20VIE%202026-07-10%202026-07-13",
      "scraped_at": "2026-06-05T22:24:17.116813",
      "data_source": "url_html"
    },
    {
      "route": "IST-DXB",
      "origin": "IST",
      "dest": "DXB",
      "depart_date": "2026-07-10",
      "return_date": "2026-07-13",
      "price": 2404.0,
      "airline": "Çeşitli",
      "target": 2200,
      "alarm_threshold": 1100,
      "savings_pct": -9,
      "is_below_target": false,
      "is_mistake_fare": true,
      "has_stopover": true,
      "google_link": "https://www.google.com/travel/flights?hl=tr&curr=TRY&gl=TR&q=IST%20to%20DXB%202026-07-10%202026-07-13",
      "scraped_at": "2026-06-05T22:26:56.018689",
      "data_source": "url_html"
    },
    {
      "route": "IST-JFK",
      "origin": "IST",
      "dest": "JFK",
      "depart_date": "2026-09-11",
      "return_date": "2026-09-14",
      "price": 2404.0,
      "airline": "Çeşitli",
      "target": 18000,
      "alarm_threshold": 9000,
      "savings_pct": 87,
      "is_below_target": false,
      "is_mistake_fare": true,
      "has_stopover": true,
      "google_link": "https://www.google.com/travel/flights?hl=tr&curr=TRY&gl=TR&q=IST%20to%20JFK%202026-09-11%202026-09-14",
      "scraped_at": "2026-06-05T22:27:49.356212",
      "data_source": "url_html"
    },
    {
      "route": "SAW-AMS",
      "origin": "SAW",
      "dest": "AMS",
      "depart_date": "2026-09-11",
      "return_date": "2026-09-14",
      "price": 2404.0,
      "airline": "Çeşitli",
      "target": 2600,
      "alarm_threshold": 1300,
      "savings_pct": 8,
      "is_below_target": false,
      "is_mistake_fare": true,
      "has_stopover": true,
      "google_link": "https://www.google.com/travel/flights?hl=tr&curr=TRY&gl=TR&q=SAW%20to%20AMS%202026-09-11%202026-09-14",
      "scraped_at": "2026-06-05T22:31:35.379387",
      "data_source": "url_html"
    },
    {
      "route": "SAW-BCN",
      "origin": "SAW",
      "dest": "BCN",
      "depart_date": "2026-09-11",
      "return_date": "2026-09-14",
      "price": 2404.0,
      "airline": "Çeşitli",
      "target": 2700,
      "alarm_threshold": 1350,
      "savings_pct": 11,
      "is_below_target": false,
      "is_mistake_fare": true,
      "has_stopover": true,
      "google_link": "https://www.google.com/travel/flights?hl=tr&curr=TRY&gl=TR&q=SAW%20to%20BCN%202026-09-11%202026-09-14",
      "scraped_at": "2026-06-05T22:33:04.017393",
      "data_source": "url_html"
    },
    {
      "route": "SAW-FCO",
      "origin": "SAW",
      "dest": "FCO",
      "depart_date": "2026-07-10",
      "return_date": "2026-07-13",
      "price": 2404.0,
      "airline": "Çeşitli",
      "target": 2400,
      "alarm_threshold": 1200,
      "savings_pct": 0,
      "is_below_target": false,
      "is_mistake_fare": true,
      "has_stopover": true,
      "google_link": "https://www.google.com/travel/flights?hl=tr&curr=TRY&gl=TR&q=SAW%20to%20FCO%202026-07-10%202026-07-13",
      "scraped_at": "2026-06-05T22:33:31.684890",
      "data_source": "url_html"
    },
    {
      "route": "IST-CDG",
      "origin": "IST",
      "dest": "CDG",
      "depart_date": "2026-09-11",
      "return_date": "2026-09-14",
      "price": 2509.0,
      "airline": "Çeşitli",
      "target": 3000,
      "alarm_threshold": 1500,
      "savings_pct": 16,
      "is_below_target": false,
      "is_mistake_fare": true,
      "has_stopover": true,
      "google_link": "https://www.google.com/travel/flights?hl=tr&curr=TRY&gl=TR&q=IST%20to%20CDG%202026-09-11%202026-09-14",
      "scraped_at": "2026-06-05T22:16:46.591328",
      "data_source": "url_html"
    },
    {
      "route": "IST-LHR",
      "origin": "IST",
      "dest": "LHR",
      "depart_date": "2026-09-11",
      "return_date": "2026-09-14",
      "price": 2509.0,
      "airline": "Çeşitli",
      "target": 3200,
      "alarm_threshold": 1600,
      "savings_pct": 22,
      "is_below_target": false,
      "is_mistake_fare": true,
      "has_stopover": true,
      "google_link": "https://www.google.com/travel/flights?hl=tr&curr=TRY&gl=TR&q=IST%20to%20LHR%202026-09-11%202026-09-14",
      "scraped_at": "2026-06-05T22:18:05.093432",
      "data_source": "url_html"
    },
    {
      "route": "IST-FRA",
      "origin": "IST",
      "dest": "FRA",
      "depart_date": "2026-07-10",
      "return_date": "2026-07-13",
      "price": 2509.0,
      "airline": "Çeşitli",
      "target": 2700,
      "alarm_threshold": 1350,
      "savings_pct": 7,
      "is_below_target": false,
      "is_mistake_fare": true,
      "has_stopover": true,
      "google_link": "https://www.google.com/travel/flights?hl=tr&curr=TRY&gl=TR&q=IST%20to%20FRA%202026-07-10%202026-07-13",
      "scraped_at": "2026-06-05T22:22:13.750343",
      "data_source": "url_html"
    },
    {
      "route": "IST-VIE",
      "origin": "IST",
      "dest": "VIE",
      "depart_date": "2026-07-10",
      "return_date": "2026-07-13",
      "price": 2509.0,
      "airline": "Çeşitli",
      "target": 2400,
      "alarm_threshold": 1200,
      "savings_pct": -5,
      "is_below_target": false,
      "is_mistake_fare": true,
      "has_stopover": true,
      "google_link": "https://www.google.com/travel/flights?hl=tr&curr=TRY&gl=TR&q=IST%20to%20VIE%202026-07-10%202026-07-13",
      "scraped_at": "2026-06-05T22:24:17.116813",
      "data_source": "url_html"
    },
    {
      "route": "IST-DXB",
      "origin": "IST",
      "dest": "DXB",
      "depart_date": "2026-07-10",
      "return_date": "2026-07-13",
      "price": 2509.0,
      "airline": "Çeşitli",
      "target": 2200,
      "alarm_threshold": 1100,
      "savings_pct": -14,
      "is_below_target": false,
      "is_mistake_fare": true,
      "has_stopover": true,
      "google_link": "https://www.google.com/travel/flights?hl=tr&curr=TRY&gl=TR&q=IST%20to%20DXB%202026-07-10%202026-07-13",
      "scraped_at": "2026-06-05T22:26:56.018689",
      "data_source": "url_html"
    },
    {
      "route": "IST-JFK",
      "origin": "IST",
      "dest": "JFK",
      "depart_date": "2026-09-11",
      "return_date": "2026-09-14",
      "price": 2509.0,
      "airline": "Çeşitli",
      "target": 18000,
      "alarm_threshold": 9000,
      "savings_pct": 86,
      "is_below_target": false,
      "is_mistake_fare": true,
      "has_stopover": true,
      "google_link": "https://www.google.com/travel/flights?hl=tr&curr=TRY&gl=TR&q=IST%20to%20JFK%202026-09-11%202026-09-14",
      "scraped_at": "2026-06-05T22:27:49.356212",
      "data_source": "url_html"
    },
    {
      "route": "SAW-AMS",
      "origin": "SAW",
      "dest": "AMS",
      "depart_date": "2026-09-11",
      "return_date": "2026-09-14",
      "price": 2509.0,
      "airline": "Çeşitli",
      "target": 2600,
      "alarm_threshold": 1300,
      "savings_pct": 4,
      "is_below_target": false,
      "is_mistake_fare": true,
      "has_stopover": true,
      "google_link": "https://www.google.com/travel/flights?hl=tr&curr=TRY&gl=TR&q=SAW%20to%20AMS%202026-09-11%202026-09-14",
      "scraped_at": "2026-06-05T22:31:35.379387",
      "data_source": "url_html"
    },
    {
      "route": "SAW-BCN",
      "origin": "SAW",
      "dest": "BCN",
      "depart_date": "2026-09-11",
      "return_date": "2026-09-14",
      "price": 2509.0,
      "airline": "Çeşitli",
      "target": 2700,
      "alarm_threshold": 1350,
      "savings_pct": 7,
      "is_below_target": false,
      "is_mistake_fare": true,
      "has_stopover": true,
      "google_link": "https://www.google.com/travel/flights?hl=tr&curr=TRY&gl=TR&q=SAW%20to%20BCN%202026-09-11%202026-09-14",
      "scraped_at": "2026-06-05T22:33:04.017393",
      "data_source": "url_html"
    },
    {
      "route": "SAW-FCO",
      "origin": "SAW",
      "dest": "FCO",
      "depart_date": "2026-07-10",
      "return_date": "2026-07-13",
      "price": 2509.0,
      "airline": "Çeşitli",
      "target": 2400,
      "alarm_threshold": 1200,
      "savings_pct": -5,
      "is_below_target": false,
      "is_mistake_fare": true,
      "has_stopover": true,
      "google_link": "https://www.google.com/travel/flights?hl=tr&curr=TRY&gl=TR&q=SAW%20to%20FCO%202026-07-10%202026-07-13",
      "scraped_at": "2026-06-05T22:33:31.684890",
      "data_source": "url_html"
    },
    {
      "route": "IST-CDG",
      "origin": "IST",
      "dest": "CDG",
      "depart_date": "2026-09-11",
      "return_date": "2026-09-14",
      "price": 2806.0,
      "airline": "Çeşitli",
      "target": 3000,
      "alarm_threshold": 1500,
      "savings_pct": 6,
      "is_below_target": false,
      "is_mistake_fare": true,
      "has_stopover": true,
      "google_link": "https://www.google.com/travel/flights?hl=tr&curr=TRY&gl=TR&q=IST%20to%20CDG%202026-09-11%202026-09-14",
      "scraped_at": "2026-06-05T22:16:46.591328",
      "data_source": "url_html"
    },
    {
      "route": "IST-LHR",
      "origin": "IST",
      "dest": "LHR",
      "depart_date": "2026-09-11",
      "return_date": "2026-09-14",
      "price": 2806.0,
      "airline": "Çeşitli",
      "target": 3200,
      "alarm_threshold": 1600,
      "savings_pct": 12,
      "is_below_target": false,
      "is_mistake_fare": true,
      "has_stopover": true,
      "google_link": "https://www.google.com/travel/flights?hl=tr&curr=TRY&gl=TR&q=IST%20to%20LHR%202026-09-11%202026-09-14",
      "scraped_at": "2026-06-05T22:18:05.093432",
      "data_source": "url_html"
    },
    {
      "route": "IST-FRA",
      "origin": "IST",
      "dest": "FRA",
      "depart_date": "2026-07-10",
      "return_date": "2026-07-13",
      "price": 2806.0,
      "airline": "Çeşitli",
      "target": 2700,
      "alarm_threshold": 1350,
      "savings_pct": -4,
      "is_below_target": false,
      "is_mistake_fare": true,
      "has_stopover": true,
      "google_link": "https://www.google.com/travel/flights?hl=tr&curr=TRY&gl=TR&q=IST%20to%20FRA%202026-07-10%202026-07-13",
      "scraped_at": "2026-06-05T22:22:13.750343",
      "data_source": "url_html"
    },
    {
      "route": "IST-VIE",
      "origin": "IST",
      "dest": "VIE",
      "depart_date": "2026-07-10",
      "return_date": "2026-07-13",
      "price": 2806.0,
      "airline": "Çeşitli",
      "target": 2400,
      "alarm_threshold": 1200,
      "savings_pct": -17,
      "is_below_target": false,
      "is_mistake_fare": true,
      "has_stopover": true,
      "google_link": "https://www.google.com/travel/flights?hl=tr&curr=TRY&gl=TR&q=IST%20to%20VIE%202026-07-10%202026-07-13",
      "scraped_at": "2026-06-05T22:24:17.116813",
      "data_source": "url_html"
    },
    {
      "route": "IST-DXB",
      "origin": "IST",
      "dest": "DXB",
      "depart_date": "2026-07-10",
      "return_date": "2026-07-13",
      "price": 2806.0,
      "airline": "Çeşitli",
      "target": 2200,
      "alarm_threshold": 1100,
      "savings_pct": -28,
      "is_below_target": false,
      "is_mistake_fare": true,
      "has_stopover": true,
      "google_link": "https://www.google.com/travel/flights?hl=tr&curr=TRY&gl=TR&q=IST%20to%20DXB%202026-07-10%202026-07-13",
      "scraped_at": "2026-06-05T22:26:56.018689",
      "data_source": "url_html"
    },
    {
      "route": "IST-JFK",
      "origin": "IST",
      "dest": "JFK",
      "depart_date": "2026-09-11",
      "return_date": "2026-09-14",
      "price": 2806.0,
      "airline": "Çeşitli",
      "target": 18000,
      "alarm_threshold": 9000,
      "savings_pct": 84,
      "is_below_target": false,
      "is_mistake_fare": true,
      "has_stopover": true,
      "google_link": "https://www.google.com/travel/flights?hl=tr&curr=TRY&gl=TR&q=IST%20to%20JFK%202026-09-11%202026-09-14",
      "scraped_at": "2026-06-05T22:27:49.356212",
      "data_source": "url_html"
    },
    {
      "route": "SAW-AMS",
      "origin": "SAW",
      "dest": "AMS",
      "depart_date": "2026-09-11",
      "return_date": "2026-09-14",
      "price": 2806.0,
      "airline": "Çeşitli",
      "target": 2600,
      "alarm_threshold": 1300,
      "savings_pct": -8,
      "is_below_target": false,
      "is_mistake_fare": true,
      "has_stopover": true,
      "google_link": "https://www.google.com/travel/flights?hl=tr&curr=TRY&gl=TR&q=SAW%20to%20AMS%202026-09-11%202026-09-14",
      "scraped_at": "2026-06-05T22:31:35.379387",
      "data_source": "url_html"
    },
    {
      "route": "SAW-BCN",
      "origin": "SAW",
      "dest": "BCN",
      "depart_date": "2026-09-11",
      "return_date": "2026-09-14",
      "price": 2806.0,
      "airline": "Çeşitli",
      "target": 2700,
      "alarm_threshold": 1350,
      "savings_pct": -4,
      "is_below_target": false,
      "is_mistake_fare": true,
      "has_stopover": true,
      "google_link": "https://www.google.com/travel/flights?hl=tr&curr=TRY&gl=TR&q=SAW%20to%20BCN%202026-09-11%202026-09-14",
      "scraped_at": "2026-06-05T22:33:04.017393",
      "data_source": "url_html"
    },
    {
      "route": "SAW-FCO",
      "origin": "SAW",
      "dest": "FCO",
      "depart_date": "2026-07-10",
      "return_date": "2026-07-13",
      "price": 2806.0,
      "airline": "Çeşitli",
      "target": 2400,
      "alarm_threshold": 1200,
      "savings_pct": -17,
      "is_below_target": false,
      "is_mistake_fare": true,
      "has_stopover": true,
      "google_link": "https://www.google.com/travel/flights?hl=tr&curr=TRY&gl=TR&q=SAW%20to%20FCO%202026-07-10%202026-07-13",
      "scraped_at": "2026-06-05T22:33:31.684890",
      "data_source": "url_html"
    },
    {
      "route": "IST-CDG",
      "origin": "IST",
      "dest": "CDG",
      "depart_date": "2026-09-11",
      "return_date": "2026-09-14",
      "price": 3210.0,
      "airline": "Çeşitli",
      "target": 3000,
      "alarm_threshold": 1500,
      "savings_pct": -7,
      "is_below_target": false,
      "is_mistake_fare": true,
      "has_stopover": true,
      "google_link": "https://www.google.com/travel/flights?hl=tr&curr=TRY&gl=TR&q=IST%20to%20CDG%202026-09-11%202026-09-14",
      "scraped_at": "2026-06-05T22:16:46.591328",
      "data_source": "url_html"
    },
    {
      "route": "IST-LHR",
      "origin": "IST",
      "dest": "LHR",
      "depart_date": "2026-09-11",
      "return_date": "2026-09-14",
      "price": 3210.0,
      "airline": "Çeşitli",
      "target": 3200,
      "alarm_threshold": 1600,
      "savings_pct": 0,
      "is_below_target": false,
      "is_mistake_fare": true,
      "has_stopover": true,
      "google_link": "https://www.google.com/travel/flights?hl=tr&curr=TRY&gl=TR&q=IST%20to%20LHR%202026-09-11%202026-09-14",
      "scraped_at": "2026-06-05T22:18:05.093432",
      "data_source": "url_html"
    },
    {
      "route": "IST-FRA",
      "origin": "IST",
      "dest": "FRA",
      "depart_date": "2026-07-10",
      "return_date": "2026-07-13",
      "price": 3210.0,
      "airline": "Çeşitli",
      "target": 2700,
      "alarm_threshold": 1350,
      "savings_pct": -19,
      "is_below_target": false,
      "is_mistake_fare": true,
      "has_stopover": true,
      "google_link": "https://www.google.com/travel/flights?hl=tr&curr=TRY&gl=TR&q=IST%20to%20FRA%202026-07-10%202026-07-13",
      "scraped_at": "2026-06-05T22:22:13.750343",
      "data_source": "url_html"
    },
    {
      "route": "IST-VIE",
      "origin": "IST",
      "dest": "VIE",
      "depart_date": "2026-07-10",
      "return_date": "2026-07-13",
      "price": 3210.0,
      "airline": "Çeşitli",
      "target": 2400,
      "alarm_threshold": 1200,
      "savings_pct": -34,
      "is_below_target": false,
      "is_mistake_fare": true,
      "has_stopover": true,
      "google_link": "https://www.google.com/travel/flights?hl=tr&curr=TRY&gl=TR&q=IST%20to%20VIE%202026-07-10%202026-07-13",
      "scraped_at": "2026-06-05T22:24:17.116813",
      "data_source": "url_html"
    },
    {
      "route": "IST-DXB",
      "origin": "IST",
      "dest": "DXB",
      "depart_date": "2026-07-10",
      "return_date": "2026-07-13",
      "price": 3210.0,
      "airline": "Çeşitli",
      "target": 2200,
      "alarm_threshold": 1100,
      "savings_pct": -46,
      "is_below_target": false,
      "is_mistake_fare": true,
      "has_stopover": true,
      "google_link": "https://www.google.com/travel/flights?hl=tr&curr=TRY&gl=TR&q=IST%20to%20DXB%202026-07-10%202026-07-13",
      "scraped_at": "2026-06-05T22:26:56.018689",
      "data_source": "url_html"
    },
    {
      "route": "IST-JFK",
      "origin": "IST",
      "dest": "JFK",
      "depart_date": "2026-09-11",
      "return_date": "2026-09-14",
      "price": 3210.0,
      "airline": "Çeşitli",
      "target": 18000,
      "alarm_threshold": 9000,
      "savings_pct": 82,
      "is_below_target": false,
      "is_mistake_fare": true,
      "has_stopover": true,
      "google_link": "https://www.google.com/travel/flights?hl=tr&curr=TRY&gl=TR&q=IST%20to%20JFK%202026-09-11%202026-09-14",
      "scraped_at": "2026-06-05T22:27:49.356212",
      "data_source": "url_html"
    },
    {
      "route": "SAW-AMS",
      "origin": "SAW",
      "dest": "AMS",
      "depart_date": "2026-09-11",
      "return_date": "2026-09-14",
      "price": 3210.0,
      "airline": "Çeşitli",
      "target": 2600,
      "alarm_threshold": 1300,
      "savings_pct": -23,
      "is_below_target": false,
      "is_mistake_fare": true,
      "has_stopover": true,
      "google_link": "https://www.google.com/travel/flights?hl=tr&curr=TRY&gl=TR&q=SAW%20to%20AMS%202026-09-11%202026-09-14",
      "scraped_at": "2026-06-05T22:31:35.379387",
      "data_source": "url_html"
    },
    {
      "route": "SAW-BCN",
      "origin": "SAW",
      "dest": "BCN",
      "depart_date": "2026-09-11",
      "return_date": "2026-09-14",
      "price": 3210.0,
      "airline": "Çeşitli",
      "target": 2700,
      "alarm_threshold": 1350,
      "savings_pct": -19,
      "is_below_target": false,
      "is_mistake_fare": true,
      "has_stopover": true,
      "google_link": "https://www.google.com/travel/flights?hl=tr&curr=TRY&gl=TR&q=SAW%20to%20BCN%202026-09-11%202026-09-14",
      "scraped_at": "2026-06-05T22:33:04.017393",
      "data_source": "url_html"
    },
    {
      "route": "SAW-FCO",
      "origin": "SAW",
      "dest": "FCO",
      "depart_date": "2026-07-10",
      "return_date": "2026-07-13",
      "price": 3210.0,
      "airline": "Çeşitli",
      "target": 2400,
      "alarm_threshold": 1200,
      "savings_pct": -34,
      "is_below_target": false,
      "is_mistake_fare": true,
      "has_stopover": true,
      "google_link": "https://www.google.com/travel/flights?hl=tr&curr=TRY&gl=TR&q=SAW%20to%20FCO%202026-07-10%202026-07-13",
      "scraped_at": "2026-06-05T22:33:31.684890",
      "data_source": "url_html"
    },
    {
      "route": "IST-ATH",
      "origin": "IST",
      "dest": "ATH",
      "depart_date": "2026-07-31",
      "return_date": "2026-08-03",
      "price": 7472.0,
      "airline": "Çeşitli",
      "target": 1800,
      "alarm_threshold": 900,
      "savings_pct": -315,
      "is_below_target": false,
      "is_mistake_fare": false,
      "has_stopover": false,
      "google_link": "https://www.google.com/travel/flights?hl=tr&curr=TRY&gl=TR&q=IST%20to%20ATH%202026-07-31%202026-08-03",
      "scraped_at": "2026-06-05T22:26:29.664720",
      "data_source": "playwright_dom"
    },
    {
      "route": "IST-ATH",
      "origin": "IST",
      "dest": "ATH",
      "depart_date": "2026-07-31",
      "return_date": "2026-08-03",
      "price": 7736.0,
      "airline": "Çeşitli",
      "target": 1800,
      "alarm_threshold": 900,
      "savings_pct": -330,
      "is_below_target": false,
      "is_mistake_fare": false,
      "has_stopover": false,
      "google_link": "https://www.google.com/travel/flights?hl=tr&curr=TRY&gl=TR&q=IST%20to%20ATH%202026-07-31%202026-08-03",
      "scraped_at": "2026-06-05T22:26:29.664720",
      "data_source": "playwright_dom"
    },
    {
      "route": "IST-CDG",
      "origin": "IST",
      "dest": "CDG",
      "depart_date": "2026-07-31",
      "return_date": "2026-08-03",
      "price": 8000.0,
      "airline": "Çeşitli",
      "target": 3000,
      "alarm_threshold": 1500,
      "savings_pct": -167,
      "is_below_target": false,
      "is_mistake_fare": true,
      "has_stopover": true,
      "google_link": "https://www.google.com/travel/flights?hl=tr&curr=TRY&gl=TR&q=IST%20to%20CDG%202026-07-31%202026-08-03",
      "scraped_at": "2026-06-05T22:17:11.515860",
      "data_source": "url_html"
    },
    {
      "route": "IST-AMS",
      "origin": "IST",
      "dest": "AMS",
      "depart_date": "2026-07-03",
      "return_date": "2026-07-06",
      "price": 8000.0,
      "airline": "Çeşitli",
      "target": 2800,
      "alarm_threshold": 1400,
      "savings_pct": -186,
      "is_below_target": false,
      "is_mistake_fare": true,
      "has_stopover": true,
      "google_link": "https://www.google.com/travel/flights?hl=tr&curr=TRY&gl=TR&q=IST%20to%20AMS%202026-07-03%202026-07-06",
      "scraped_at": "2026-06-05T22:18:32.128762",
      "data_source": "url_html"
    },
    {
      "route": "IST-AMS",
      "origin": "IST",
      "dest": "AMS",
      "depart_date": "2026-07-17",
      "return_date": "2026-07-20",
      "price": 8000.0,
      "airline": "Çeşitli",
      "target": 2800,
      "alarm_threshold": 1400,
      "savings_pct": -186,
      "is_below_target": false,
      "is_mistake_fare": true,
      "has_stopover": true,
      "google_link": "https://www.google.com/travel/flights?hl=tr&curr=TRY&gl=TR&q=IST%20to%20AMS%202026-07-17%202026-07-20",
      "scraped_at": "2026-06-05T22:19:03.729907",
      "data_source": "url_html"
    },
    {
      "route": "IST-MAD",
      "origin": "IST",
      "dest": "MAD",
      "depart_date": "2026-06-26",
      "return_date": "2026-06-29",
      "price": 8000.0,
      "airline": "Çeşitli",
      "target": 3100,
      "alarm_threshold": 1550,
      "savings_pct": -158,
      "is_below_target": false,
      "is_mistake_fare": true,
      "has_stopover": true,
      "google_link": "https://www.google.com/travel/flights?hl=tr&curr=TRY&gl=TR&q=IST%20to%20MAD%202026-06-26%202026-06-29",
      "scraped_at": "2026-06-05T22:21:16.009849",
      "data_source": "url_html"
    },
    {
      "route": "IST-FRA",
      "origin": "IST",
      "dest": "FRA",
      "depart_date": "2026-07-17",
      "return_date": "2026-07-20",
      "price": 8000.0,
      "airline": "Çeşitli",
      "target": 2700,
      "alarm_threshold": 1350,
      "savings_pct": -196,
      "is_below_target": false,
      "is_mistake_fare": true,
      "has_stopover": true,
      "google_link": "https://www.google.com/travel/flights?hl=tr&curr=TRY&gl=TR&q=IST%20to%20FRA%202026-07-17%202026-07-20",
      "scraped_at": "2026-06-05T22:22:46.161188",
      "data_source": "url_html"
    },
    {
      "route": "IST-VIE",
      "origin": "IST",
      "dest": "VIE",
      "depart_date": "2026-08-28",
      "return_date": "2026-08-31",
      "price": 8000.0,
      "airline": "Çeşitli",
      "target": 2400,
      "alarm_threshold": 1200,
      "savings_pct": -233,
      "is_below_target": false,
      "is_mistake_fare": true,
      "has_stopover": true,
      "google_link": "https://www.google.com/travel/flights?hl=tr&curr=TRY&gl=TR&q=IST%20to%20VIE%202026-08-28%202026-08-31",
      "scraped_at": "2026-06-05T22:24:42.574027",
      "data_source": "url_html"
    },
    {
      "route": "IST-DXB",
      "origin": "IST",
      "dest": "DXB",
      "depart_date": "2026-09-25",
      "return_date": "2026-09-28",
      "price": 8000.0,
      "airline": "Çeşitli",
      "target": 2200,
      "alarm_threshold": 1100,
      "savings_pct": -264,
      "is_below_target": false,
      "is_mistake_fare": true,
      "has_stopover": true,
      "google_link": "https://www.google.com/travel/flights?hl=tr&curr=TRY&gl=TR&q=IST%20to%20DXB%202026-09-25%202026-09-28",
      "scraped_at": "2026-06-05T22:27:23.841687",
      "data_source": "url_html"
    },
    {
      "route": "SAW-CDG",
      "origin": "SAW",
      "dest": "CDG",
      "depart_date": "2026-07-03",
      "return_date": "2026-07-06",
      "price": 8000.0,
      "airline": "Çeşitli",
      "target": 2800,
      "alarm_threshold": 1400,
      "savings_pct": -186,
      "is_below_target": false,
      "is_mistake_fare": true,
      "has_stopover": true,
      "google_link": "https://www.google.com/travel/flights?hl=tr&curr=TRY&gl=TR&q=SAW%20to%20CDG%202026-07-03%202026-07-06",
      "scraped_at": "2026-06-05T22:29:41.274943",
      "data_source": "url_html"
    },
    {
      "route": "SAW-CDG",
      "origin": "SAW",
      "dest": "CDG",
      "depart_date": "2026-08-14",
      "return_date": "2026-08-17",
      "price": 8000.0,
      "airline": "Çeşitli",
      "target": 2800,
      "alarm_threshold": 1400,
      "savings_pct": -186,
      "is_below_target": false,
      "is_mistake_fare": true,
      "has_stopover": true,
      "google_link": "https://www.google.com/travel/flights?hl=tr&curr=TRY&gl=TR&q=SAW%20to%20CDG%202026-08-14%202026-08-17",
      "scraped_at": "2026-06-05T22:30:13.766325",
      "data_source": "url_html"
    },
    {
      "route": "SAW-LHR",
      "origin": "SAW",
      "dest": "LHR",
      "depart_date": "2026-06-26",
      "return_date": "2026-06-29",
      "price": 8000.0,
      "airline": "Çeşitli",
      "target": 3000,
      "alarm_threshold": 1500,
      "savings_pct": -167,
      "is_below_target": false,
      "is_mistake_fare": true,
      "has_stopover": true,
      "google_link": "https://www.google.com/travel/flights?hl=tr&curr=TRY&gl=TR&q=SAW%20to%20LHR%202026-06-26%202026-06-29",
      "scraped_at": "2026-06-05T22:30:39.196754",
      "data_source": "url_html"
    },
    {
      "route": "SAW-LHR",
      "origin": "SAW",
      "dest": "LHR",
      "depart_date": "2026-07-17",
      "return_date": "2026-07-20",
      "price": 8000.0,
      "airline": "Çeşitli",
      "target": 3000,
      "alarm_threshold": 1500,
      "savings_pct": -167,
      "is_below_target": false,
      "is_mistake_fare": true,
      "has_stopover": true,
      "google_link": "https://www.google.com/travel/flights?hl=tr&curr=TRY&gl=TR&q=SAW%20to%20LHR%202026-07-17%202026-07-20",
      "scraped_at": "2026-06-05T22:31:06.081869",
      "data_source": "url_html"
    },
    {
      "route": "SAW-BCN",
      "origin": "SAW",
      "dest": "BCN",
      "depart_date": "2026-06-19",
      "return_date": "2026-06-22",
      "price": 8000.0,
      "airline": "Çeşitli",
      "target": 2700,
      "alarm_threshold": 1350,
      "savings_pct": -196,
      "is_below_target": false,
      "is_mistake_fare": true,
      "has_stopover": true,
      "google_link": "https://www.google.com/travel/flights?hl=tr&curr=TRY&gl=TR&q=SAW%20to%20BCN%202026-06-19%202026-06-22",
      "scraped_at": "2026-06-05T22:32:33.188575",
      "data_source": "url_html"
    },
    {
      "route": "SAW-FCO",
      "origin": "SAW",
      "dest": "FCO",
      "depart_date": "2026-07-17",
      "return_date": "2026-07-20",
      "price": 8000.0,
      "airline": "Çeşitli",
      "target": 2400,
      "alarm_threshold": 1200,
      "savings_pct": -233,
      "is_below_target": false,
      "is_mistake_fare": true,
      "has_stopover": true,
      "google_link": "https://www.google.com/travel/flights?hl=tr&curr=TRY&gl=TR&q=SAW%20to%20FCO%202026-07-17%202026-07-20",
      "scraped_at": "2026-06-05T22:34:00.335780",
      "data_source": "url_html"
    },
    {
      "route": "IST-MUC",
      "origin": "IST",
      "dest": "MUC",
      "depart_date": "2026-06-19",
      "return_date": "2026-06-22",
      "price": 8674.0,
      "airline": "Çeşitli",
      "target": 2500,
      "alarm_threshold": 1250,
      "savings_pct": -247,
      "is_below_target": false,
      "is_mistake_fare": false,
      "has_stopover": false,
      "google_link": "https://www.google.com/travel/flights?hl=tr&curr=TRY&gl=TR&q=IST%20to%20MUC%202026-06-19%202026-06-22",
      "scraped_at": "2026-06-05T22:23:18.634673",
      "data_source": "playwright_dom"
    },
    {
      "route": "IST-ATH",
      "origin": "IST",
      "dest": "ATH",
      "depart_date": "2026-07-31",
      "return_date": "2026-08-03",
      "price": 9066.0,
      "airline": "Çeşitli",
      "target": 1800,
      "alarm_threshold": 900,
      "savings_pct": -404,
      "is_below_target": false,
      "is_mistake_fare": false,
      "has_stopover": false,
      "google_link": "https://www.google.com/travel/flights?hl=tr&curr=TRY&gl=TR&q=IST%20to%20ATH%202026-07-31%202026-08-03",
      "scraped_at": "2026-06-05T22:26:29.664720",
      "data_source": "playwright_dom"
    },
    {
      "route": "IST-ATH",
      "origin": "IST",
      "dest": "ATH",
      "depart_date": "2026-07-31",
      "return_date": "2026-08-03",
      "price": 9209.0,
      "airline": "Çeşitli",
      "target": 1800,
      "alarm_threshold": 900,
      "savings_pct": -412,
      "is_below_target": false,
      "is_mistake_fare": false,
      "has_stopover": false,
      "google_link": "https://www.google.com/travel/flights?hl=tr&curr=TRY&gl=TR&q=IST%20to%20ATH%202026-07-31%202026-08-03",
      "scraped_at": "2026-06-05T22:26:29.664720",
      "data_source": "playwright_dom"
    },
    {
      "route": "IST-ATH",
      "origin": "IST",
      "dest": "ATH",
      "depart_date": "2026-06-19",
      "return_date": "2026-06-22",
      "price": 9541.0,
      "airline": "Çeşitli",
      "target": 1800,
      "alarm_threshold": 900,
      "savings_pct": -430,
      "is_below_target": false,
      "is_mistake_fare": false,
      "has_stopover": false,
      "google_link": "https://www.google.com/travel/flights?hl=tr&curr=TRY&gl=TR&q=IST%20to%20ATH%202026-06-19%202026-06-22",
      "scraped_at": "2026-06-05T22:26:04.537573",
      "data_source": "playwright_dom"
    },
    {
      "route": "SAW-LHR",
      "origin": "SAW",
      "dest": "LHR",
      "depart_date": "2026-06-26",
      "return_date": "2026-06-29",
      "price": 9547.0,
      "airline": "Çeşitli",
      "target": 3000,
      "alarm_threshold": 1500,
      "savings_pct": -218,
      "is_below_target": false,
      "is_mistake_fare": true,
      "has_stopover": true,
      "google_link": "https://www.google.com/travel/flights?hl=tr&curr=TRY&gl=TR&q=SAW%20to%20LHR%202026-06-26%202026-06-29",
      "scraped_at": "2026-06-05T22:30:39.196754",
      "data_source": "url_html"
    },
    {
      "route": "IST-FCO",
      "origin": "IST",
      "dest": "FCO",
      "depart_date": "2026-09-25",
      "return_date": "2026-09-28",
      "price": 10196.0,
      "airline": "Çeşitli",
      "target": 2600,
      "alarm_threshold": 1300,
      "savings_pct": -292,
      "is_below_target": false,
      "is_mistake_fare": false,
      "has_stopover": false,
      "google_link": "https://www.google.com/travel/flights?hl=tr&curr=TRY&gl=TR&q=IST%20to%20FCO%202026-09-25%202026-09-28",
      "scraped_at": "2026-06-05T22:20:49.191840",
      "data_source": "playwright_dom"
    },
    {
      "route": "IST-FCO",
      "origin": "IST",
      "dest": "FCO",
      "depart_date": "2026-09-25",
      "return_date": "2026-09-28",
      "price": 10857.0,
      "airline": "Çeşitli",
      "target": 2600,
      "alarm_threshold": 1300,
      "savings_pct": -318,
      "is_below_target": false,
      "is_mistake_fare": false,
      "has_stopover": false,
      "google_link": "https://www.google.com/travel/flights?hl=tr&curr=TRY&gl=TR&q=IST%20to%20FCO%202026-09-25%202026-09-28",
      "scraped_at": "2026-06-05T22:20:49.191840",
      "data_source": "playwright_dom"
    },
    {
      "route": "IST-MUC",
      "origin": "IST",
      "dest": "MUC",
      "depart_date": "2026-07-03",
      "return_date": "2026-07-06",
      "price": 10930.0,
      "airline": "Çeşitli",
      "target": 2500,
      "alarm_threshold": 1250,
      "savings_pct": -337,
      "is_below_target": false,
      "is_mistake_fare": false,
      "has_stopover": false,
      "google_link": "https://www.google.com/travel/flights?hl=tr&curr=TRY&gl=TR&q=IST%20to%20MUC%202026-07-03%202026-07-06",
      "scraped_at": "2026-06-05T22:23:49.234742",
      "data_source": "playwright_dom"
    },
    {
      "route": "SAW-BCN",
      "origin": "SAW",
      "dest": "BCN",
      "depart_date": "2026-06-19",
      "return_date": "2026-06-22",
      "price": 10940.0,
      "airline": "Çeşitli",
      "target": 2700,
      "alarm_threshold": 1350,
      "savings_pct": -305,
      "is_below_target": false,
      "is_mistake_fare": true,
      "has_stopover": true,
      "google_link": "https://www.google.com/travel/flights?hl=tr&curr=TRY&gl=TR&q=SAW%20to%20BCN%202026-06-19%202026-06-22",
      "scraped_at": "2026-06-05T22:32:33.188575",
      "data_source": "url_html"
    },
    {
      "route": "IST-PRG",
      "origin": "IST",
      "dest": "PRG",
      "depart_date": "2026-08-14",
      "return_date": "2026-08-17",
      "price": 10984.0,
      "airline": "Çeşitli",
      "target": 2600,
      "alarm_threshold": 1300,
      "savings_pct": -322,
      "is_below_target": false,
      "is_mistake_fare": false,
      "has_stopover": false,
      "google_link": "https://www.google.com/travel/flights?hl=tr&curr=TRY&gl=TR&q=IST%20to%20PRG%202026-08-14%202026-08-17",
      "scraped_at": "2026-06-05T22:25:35.891875",
      "data_source": "playwright_dom"
    },
    {
      "route": "IST-BCN",
      "origin": "IST",
      "dest": "BCN",
      "depart_date": "2026-06-26",
      "return_date": "2026-06-29",
      "price": 10996.0,
      "airline": "Çeşitli",
      "target": 2900,
      "alarm_threshold": 1450,
      "savings_pct": -279,
      "is_below_target": false,
      "is_mistake_fare": false,
      "has_stopover": false,
      "google_link": "https://www.google.com/travel/flights?hl=tr&curr=TRY&gl=TR&q=IST%20to%20BCN%202026-06-26%202026-06-29",
      "scraped_at": "2026-06-05T22:19:56.377454",
      "data_source": "playwright_dom"
    },
    {
      "route": "IST-BCN",
      "origin": "IST",
      "dest": "BCN",
      "depart_date": "2026-07-17",
      "return_date": "2026-07-20",
      "price": 11361.0,
      "airline": "Çeşitli",
      "target": 2900,
      "alarm_threshold": 1450,
      "savings_pct": -292,
      "is_below_target": false,
      "is_mistake_fare": false,
      "has_stopover": false,
      "google_link": "https://www.google.com/travel/flights?hl=tr&curr=TRY&gl=TR&q=IST%20to%20BCN%202026-07-17%202026-07-20",
      "scraped_at": "2026-06-05T22:19:30.061413",
      "data_source": "playwright_dom"
    },
    {
      "route": "IST-BCN",
      "origin": "IST",
      "dest": "BCN",
      "depart_date": "2026-06-26",
      "return_date": "2026-06-29",
      "price": 11499.0,
      "airline": "Çeşitli",
      "target": 2900,
      "alarm_threshold": 1450,
      "savings_pct": -297,
      "is_below_target": false,
      "is_mistake_fare": false,
      "has_stopover": false,
      "google_link": "https://www.google.com/travel/flights?hl=tr&curr=TRY&gl=TR&q=IST%20to%20BCN%202026-06-26%202026-06-29",
      "scraped_at": "2026-06-05T22:19:56.377454",
      "data_source": "playwright_dom"
    },
    {
      "route": "IST-MUC",
      "origin": "IST",
      "dest": "MUC",
      "depart_date": "2026-06-19",
      "return_date": "2026-06-22",
      "price": 11523.0,
      "airline": "Çeşitli",
      "target": 2500,
      "alarm_threshold": 1250,
      "savings_pct": -361,
      "is_below_target": false,
      "is_mistake_fare": false,
      "has_stopover": false,
      "google_link": "https://www.google.com/travel/flights?hl=tr&curr=TRY&gl=TR&q=IST%20to%20MUC%202026-06-19%202026-06-22",
      "scraped_at": "2026-06-05T22:23:18.634673",
      "data_source": "playwright_dom"
    },
    {
      "route": "IST-MUC",
      "origin": "IST",
      "dest": "MUC",
      "depart_date": "2026-06-19",
      "return_date": "2026-06-22",
      "price": 11700.0,
      "airline": "Çeşitli",
      "target": 2500,
      "alarm_threshold": 1250,
      "savings_pct": -368,
      "is_below_target": false,
      "is_mistake_fare": false,
      "has_stopover": false,
      "google_link": "https://www.google.com/travel/flights?hl=tr&curr=TRY&gl=TR&q=IST%20to%20MUC%202026-06-19%202026-06-22",
      "scraped_at": "2026-06-05T22:23:18.634673",
      "data_source": "playwright_dom"
    },
    {
      "route": "IST-BCN",
      "origin": "IST",
      "dest": "BCN",
      "depart_date": "2026-06-26",
      "return_date": "2026-06-29",
      "price": 11818.0,
      "airline": "Çeşitli",
      "target": 2900,
      "alarm_threshold": 1450,
      "savings_pct": -308,
      "is_below_target": false,
      "is_mistake_fare": false,
      "has_stopover": false,
      "google_link": "https://www.google.com/travel/flights?hl=tr&curr=TRY&gl=TR&q=IST%20to%20BCN%202026-06-26%202026-06-29",
      "scraped_at": "2026-06-05T22:19:56.377454",
      "data_source": "playwright_dom"
    },
    {
      "route": "SAW-AMS",
      "origin": "SAW",
      "dest": "AMS",
      "depart_date": "2026-09-25",
      "return_date": "2026-09-28",
      "price": 11920.0,
      "airline": "Çeşitli",
      "target": 2600,
      "alarm_threshold": 1300,
      "savings_pct": -358,
      "is_below_target": false,
      "is_mistake_fare": false,
      "has_stopover": false,
      "google_link": "https://www.google.com/travel/flights?hl=tr&curr=TRY&gl=TR&q=SAW%20to%20AMS%202026-09-25%202026-09-28",
      "scraped_at": "2026-06-05T22:32:04.338050",
      "data_source": "playwright_dom"
    },
    {
      "route": "SAW-AMS",
      "origin": "SAW",
      "dest": "AMS",
      "depart_date": "2026-09-25",
      "return_date": "2026-09-28",
      "price": 12326.0,
      "airline": "Çeşitli",
      "target": 2600,
      "alarm_threshold": 1300,
      "savings_pct": -374,
      "is_below_target": false,
      "is_mistake_fare": false,
      "has_stopover": false,
      "google_link": "https://www.google.com/travel/flights?hl=tr&curr=TRY&gl=TR&q=SAW%20to%20AMS%202026-09-25%202026-09-28",
      "scraped_at": "2026-06-05T22:32:04.338050",
      "data_source": "playwright_dom"
    },
    {
      "route": "IST-MAD",
      "origin": "IST",
      "dest": "MAD",
      "depart_date": "2026-07-03",
      "return_date": "2026-07-06",
      "price": 12508.0,
      "airline": "Çeşitli",
      "target": 3100,
      "alarm_threshold": 1550,
      "savings_pct": -303,
      "is_below_target": false,
      "is_mistake_fare": false,
      "has_stopover": false,
      "google_link": "https://www.google.com/travel/flights?hl=tr&curr=TRY&gl=TR&q=IST%20to%20MAD%202026-07-03%202026-07-06",
      "scraped_at": "2026-06-05T22:21:43.951306",
      "data_source": "playwright_dom"
    },
    {
      "route": "IST-PRG",
      "origin": "IST",
      "dest": "PRG",
      "depart_date": "2026-07-31",
      "return_date": "2026-08-03",
      "price": 12559.0,
      "airline": "Çeşitli",
      "target": 2600,
      "alarm_threshold": 1300,
      "savings_pct": -383,
      "is_below_target": false,
      "is_mistake_fare": false,
      "has_stopover": false,
      "google_link": "https://www.google.com/travel/flights?hl=tr&curr=TRY&gl=TR&q=IST%20to%20PRG%202026-07-31%202026-08-03",
      "scraped_at": "2026-06-05T22:25:11.177446",
      "data_source": "playwright_dom"
    },
    {
      "route": "IST-MUC",
      "origin": "IST",
      "dest": "MUC",
      "depart_date": "2026-07-03",
      "return_date": "2026-07-06",
      "price": 12856.0,
      "airline": "Çeşitli",
      "target": 2500,
      "alarm_threshold": 1250,
      "savings_pct": -414,
      "is_below_target": false,
      "is_mistake_fare": false,
      "has_stopover": false,
      "google_link": "https://www.google.com/travel/flights?hl=tr&curr=TRY&gl=TR&q=IST%20to%20MUC%202026-07-03%202026-07-06",
      "scraped_at": "2026-06-05T22:23:49.234742",
      "data_source": "playwright_dom"
    },
    {
      "route": "IST-BCN",
      "origin": "IST",
      "dest": "BCN",
      "depart_date": "2026-07-17",
      "return_date": "2026-07-20",
      "price": 12897.0,
      "airline": "Çeşitli",
      "target": 2900,
      "alarm_threshold": 1450,
      "savings_pct": -345,
      "is_below_target": false,
      "is_mistake_fare": false,
      "has_stopover": false,
      "google_link": "https://www.google.com/travel/flights?hl=tr&curr=TRY&gl=TR&q=IST%20to%20BCN%202026-07-17%202026-07-20",
      "scraped_at": "2026-06-05T22:19:30.061413",
      "data_source": "playwright_dom"
    },
    {
      "route": "IST-FCO",
      "origin": "IST",
      "dest": "FCO",
      "depart_date": "2026-08-28",
      "return_date": "2026-08-31",
      "price": 12954.0,
      "airline": "Çeşitli",
      "target": 2600,
      "alarm_threshold": 1300,
      "savings_pct": -398,
      "is_below_target": false,
      "is_mistake_fare": false,
      "has_stopover": false,
      "google_link": "https://www.google.com/travel/flights?hl=tr&curr=TRY&gl=TR&q=IST%20to%20FCO%202026-08-28%202026-08-31",
      "scraped_at": "2026-06-05T22:20:21.802708",
      "data_source": "playwright_dom"
    },
    {
      "route": "SAW-AMS",
      "origin": "SAW",
      "dest": "AMS",
      "depart_date": "2026-09-25",
      "return_date": "2026-09-28",
      "price": 13023.0,
      "airline": "Çeşitli",
      "target": 2600,
      "alarm_threshold": 1300,
      "savings_pct": -401,
      "is_below_target": false,
      "is_mistake_fare": false,
      "has_stopover": false,
      "google_link": "https://www.google.com/travel/flights?hl=tr&curr=TRY&gl=TR&q=SAW%20to%20AMS%202026-09-25%202026-09-28",
      "scraped_at": "2026-06-05T22:32:04.338050",
      "data_source": "playwright_dom"
    },
    {
      "route": "SAW-AMS",
      "origin": "SAW",
      "dest": "AMS",
      "depart_date": "2026-09-25",
      "return_date": "2026-09-28",
      "price": 13150.0,
      "airline": "Çeşitli",
      "target": 2600,
      "alarm_threshold": 1300,
      "savings_pct": -406,
      "is_below_target": false,
      "is_mistake_fare": false,
      "has_stopover": false,
      "google_link": "https://www.google.com/travel/flights?hl=tr&curr=TRY&gl=TR&q=SAW%20to%20AMS%202026-09-25%202026-09-28",
      "scraped_at": "2026-06-05T22:32:04.338050",
      "data_source": "playwright_dom"
    },
    {
      "route": "IST-MAD",
      "origin": "IST",
      "dest": "MAD",
      "depart_date": "2026-07-03",
      "return_date": "2026-07-06",
      "price": 13290.0,
      "airline": "Çeşitli",
      "target": 3100,
      "alarm_threshold": 1550,
      "savings_pct": -329,
      "is_below_target": false,
      "is_mistake_fare": false,
      "has_stopover": false,
      "google_link": "https://www.google.com/travel/flights?hl=tr&curr=TRY&gl=TR&q=IST%20to%20MAD%202026-07-03%202026-07-06",
      "scraped_at": "2026-06-05T22:21:43.951306",
      "data_source": "playwright_dom"
    },
    {
      "route": "IST-LHR",
      "origin": "IST",
      "dest": "LHR",
      "depart_date": "2026-07-03",
      "return_date": "2026-07-06",
      "price": 13658.0,
      "airline": "Çeşitli",
      "target": 3200,
      "alarm_threshold": 1600,
      "savings_pct": -327,
      "is_below_target": false,
      "is_mistake_fare": false,
      "has_stopover": false,
      "google_link": "https://www.google.com/travel/flights?hl=tr&curr=TRY&gl=TR&q=IST%20to%20LHR%202026-07-03%202026-07-06",
      "scraped_at": "2026-06-05T22:17:39.157886",
      "data_source": "playwright_dom"
    },
    {
      "route": "SAW-CDG",
      "origin": "SAW",
      "dest": "CDG",
      "depart_date": "2026-07-03",
      "return_date": "2026-07-06",
      "price": 14876.0,
      "airline": "Çeşitli",
      "target": 2800,
      "alarm_threshold": 1400,
      "savings_pct": -431,
      "is_below_target": false,
      "is_mistake_fare": true,
      "has_stopover": true,
      "google_link": "https://www.google.com/travel/flights?hl=tr&curr=TRY&gl=TR&q=SAW%20to%20CDG%202026-07-03%202026-07-06",
      "scraped_at": "2026-06-05T22:29:41.274943",
      "data_source": "url_html"
    },
    {
      "route": "IST-MAD",
      "origin": "IST",
      "dest": "MAD",
      "depart_date": "2026-07-03",
      "return_date": "2026-07-06",
      "price": 14948.0,
      "airline": "Çeşitli",
      "target": 3100,
      "alarm_threshold": 1550,
      "savings_pct": -382,
      "is_below_target": false,
      "is_mistake_fare": false,
      "has_stopover": false,
      "google_link": "https://www.google.com/travel/flights?hl=tr&curr=TRY&gl=TR&q=IST%20to%20MAD%202026-07-03%202026-07-06",
      "scraped_at": "2026-06-05T22:21:43.951306",
      "data_source": "playwright_dom"
    },
    {
      "route": "IST-LAX",
      "origin": "IST",
      "dest": "LAX",
      "depart_date": "2026-06-26",
      "return_date": "2026-06-29",
      "price": 33587.0,
      "airline": "Çeşitli",
      "target": 20000,
      "alarm_threshold": 10000,
      "savings_pct": -68,
      "is_below_target": false,
      "is_mistake_fare": false,
      "has_stopover": false,
      "google_link": "https://www.google.com/travel/flights?hl=tr&curr=TRY&gl=TR&q=IST%20to%20LAX%202026-06-26%202026-06-29",
      "scraped_at": "2026-06-05T22:29:14.162234",
      "data_source": "playwright_dom"
    },
    {
      "route": "IST-LAX",
      "origin": "IST",
      "dest": "LAX",
      "depart_date": "2026-06-26",
      "return_date": "2026-06-29",
      "price": 34057.0,
      "airline": "Çeşitli",
      "target": 20000,
      "alarm_threshold": 10000,
      "savings_pct": -70,
      "is_below_target": false,
      "is_mistake_fare": false,
      "has_stopover": false,
      "google_link": "https://www.google.com/travel/flights?hl=tr&curr=TRY&gl=TR&q=IST%20to%20LAX%202026-06-26%202026-06-29",
      "scraped_at": "2026-06-05T22:29:14.162234",
      "data_source": "playwright_dom"
    },
    {
      "route": "IST-LAX",
      "origin": "IST",
      "dest": "LAX",
      "depart_date": "2026-06-26",
      "return_date": "2026-06-29",
      "price": 34907.0,
      "airline": "Çeşitli",
      "target": 20000,
      "alarm_threshold": 10000,
      "savings_pct": -75,
      "is_below_target": false,
      "is_mistake_fare": false,
      "has_stopover": false,
      "google_link": "https://www.google.com/travel/flights?hl=tr&curr=TRY&gl=TR&q=IST%20to%20LAX%202026-06-26%202026-06-29",
      "scraped_at": "2026-06-05T22:29:14.162234",
      "data_source": "playwright_dom"
    },
    {
      "route": "IST-JFK",
      "origin": "IST",
      "dest": "JFK",
      "depart_date": "2026-08-14",
      "return_date": "2026-08-17",
      "price": 36663.0,
      "airline": "Çeşitli",
      "target": 18000,
      "alarm_threshold": 9000,
      "savings_pct": -104,
      "is_below_target": false,
      "is_mistake_fare": false,
      "has_stopover": false,
      "google_link": "https://www.google.com/travel/flights?hl=tr&curr=TRY&gl=TR&q=IST%20to%20JFK%202026-08-14%202026-08-17",
      "scraped_at": "2026-06-05T22:28:21.582931",
      "data_source": "playwright_dom"
    },
    {
      "route": "IST-JFK",
      "origin": "IST",
      "dest": "JFK",
      "depart_date": "2026-08-14",
      "return_date": "2026-08-17",
      "price": 38469.0,
      "airline": "Çeşitli",
      "target": 18000,
      "alarm_threshold": 9000,
      "savings_pct": -114,
      "is_below_target": false,
      "is_mistake_fare": false,
      "has_stopover": false,
      "google_link": "https://www.google.com/travel/flights?hl=tr&curr=TRY&gl=TR&q=IST%20to%20JFK%202026-08-14%202026-08-17",
      "scraped_at": "2026-06-05T22:28:21.582931",
      "data_source": "playwright_dom"
    },
    {
      "route": "IST-JFK",
      "origin": "IST",
      "dest": "JFK",
      "depart_date": "2026-08-14",
      "return_date": "2026-08-17",
      "price": 42384.0,
      "airline": "Çeşitli",
      "target": 18000,
      "alarm_threshold": 9000,
      "savings_pct": -135,
      "is_below_target": false,
      "is_mistake_fare": false,
      "has_stopover": false,
      "google_link": "https://www.google.com/travel/flights?hl=tr&curr=TRY&gl=TR&q=IST%20to%20JFK%202026-08-14%202026-08-17",
      "scraped_at": "2026-06-05T22:28:21.582931",
      "data_source": "playwright_dom"
    },
    {
      "route": "IST-LAX",
      "origin": "IST",
      "dest": "LAX",
      "depart_date": "2026-08-14",
      "return_date": "2026-08-17",
      "price": 43558.0,
      "airline": "Çeşitli",
      "target": 20000,
      "alarm_threshold": 10000,
      "savings_pct": -118,
      "is_below_target": false,
      "is_mistake_fare": false,
      "has_stopover": false,
      "google_link": "https://www.google.com/travel/flights?hl=tr&curr=TRY&gl=TR&q=IST%20to%20LAX%202026-08-14%202026-08-17",
      "scraped_at": "2026-06-05T22:28:48.105557",
      "data_source": "playwright_dom"
    },
    {
      "route": "IST-LAX",
      "origin": "IST",
      "dest": "LAX",
      "depart_date": "2026-06-26",
      "return_date": "2026-06-29",
      "price": 43921.0,
      "airline": "Çeşitli",
      "target": 20000,
      "alarm_threshold": 10000,
      "savings_pct": -120,
      "is_below_target": false,
      "is_mistake_fare": false,
      "has_stopover": false,
      "google_link": "https://www.google.com/travel/flights?hl=tr&curr=TRY&gl=TR&q=IST%20to%20LAX%202026-06-26%202026-06-29",
      "scraped_at": "2026-06-05T22:29:14.162234",
      "data_source": "playwright_dom"
    },
    {
      "route": "IST-JFK",
      "origin": "IST",
      "dest": "JFK",
      "depart_date": "2026-08-14",
      "return_date": "2026-08-17",
      "price": 44234.0,
      "airline": "Çeşitli",
      "target": 18000,
      "alarm_threshold": 9000,
      "savings_pct": -146,
      "is_below_target": false,
      "is_mistake_fare": false,
      "has_stopover": false,
      "google_link": "https://www.google.com/travel/flights?hl=tr&curr=TRY&gl=TR&q=IST%20to%20JFK%202026-08-14%202026-08-17",
      "scraped_at": "2026-06-05T22:28:21.582931",
      "data_source": "playwright_dom"
    },
    {
      "route": "IST-LAX",
      "origin": "IST",
      "dest": "LAX",
      "depart_date": "2026-06-26",
      "return_date": "2026-06-29",
      "price": 44611.0,
      "airline": "Çeşitli",
      "target": 20000,
      "alarm_threshold": 10000,
      "savings_pct": -123,
      "is_below_target": false,
      "is_mistake_fare": false,
      "has_stopover": false,
      "google_link": "https://www.google.com/travel/flights?hl=tr&curr=TRY&gl=TR&q=IST%20to%20LAX%202026-06-26%202026-06-29",
      "scraped_at": "2026-06-05T22:29:14.162234",
      "data_source": "playwright_dom"
    },
    {
      "route": "IST-JFK",
      "origin": "IST",
      "dest": "JFK",
      "depart_date": "2026-08-14",
      "return_date": "2026-08-17",
      "price": 46236.0,
      "airline": "Çeşitli",
      "target": 18000,
      "alarm_threshold": 9000,
      "savings_pct": -157,
      "is_below_target": false,
      "is_mistake_fare": false,
      "has_stopover": false,
      "google_link": "https://www.google.com/travel/flights?hl=tr&curr=TRY&gl=TR&q=IST%20to%20JFK%202026-08-14%202026-08-17",
      "scraped_at": "2026-06-05T22:28:21.582931",
      "data_source": "playwright_dom"
    },
    {
      "route": "IST-JFK",
      "origin": "IST",
      "dest": "JFK",
      "depart_date": "2026-08-14",
      "return_date": "2026-08-17",
      "price": 46588.0,
      "airline": "Çeşitli",
      "target": 18000,
      "alarm_threshold": 9000,
      "savings_pct": -159,
      "is_below_target": false,
      "is_mistake_fare": false,
      "has_stopover": false,
      "google_link": "https://www.google.com/travel/flights?hl=tr&curr=TRY&gl=TR&q=IST%20to%20JFK%202026-08-14%202026-08-17",
      "scraped_at": "2026-06-05T22:28:21.582931",
      "data_source": "playwright_dom"
    },
    {
      "route": "IST-LAX",
      "origin": "IST",
      "dest": "LAX",
      "depart_date": "2026-08-14",
      "return_date": "2026-08-17",
      "price": 47197.0,
      "airline": "Çeşitli",
      "target": 20000,
      "alarm_threshold": 10000,
      "savings_pct": -136,
      "is_below_target": false,
      "is_mistake_fare": false,
      "has_stopover": false,
      "google_link": "https://www.google.com/travel/flights?hl=tr&curr=TRY&gl=TR&q=IST%20to%20LAX%202026-08-14%202026-08-17",
      "scraped_at": "2026-06-05T22:28:48.105557",
      "data_source": "playwright_dom"
    },
    {
      "route": "IST-JFK",
      "origin": "IST",
      "dest": "JFK",
      "depart_date": "2026-08-14",
      "return_date": "2026-08-17",
      "price": 47435.0,
      "airline": "Çeşitli",
      "target": 18000,
      "alarm_threshold": 9000,
      "savings_pct": -164,
      "is_below_target": false,
      "is_mistake_fare": false,
      "has_stopover": false,
      "google_link": "https://www.google.com/travel/flights?hl=tr&curr=TRY&gl=TR&q=IST%20to%20JFK%202026-08-14%202026-08-17",
      "scraped_at": "2026-06-05T22:28:21.582931",
      "data_source": "playwright_dom"
    },
    {
      "route": "IST-LAX",
      "origin": "IST",
      "dest": "LAX",
      "depart_date": "2026-06-26",
      "return_date": "2026-06-29",
      "price": 47645.0,
      "airline": "Çeşitli",
      "target": 20000,
      "alarm_threshold": 10000,
      "savings_pct": -138,
      "is_below_target": false,
      "is_mistake_fare": false,
      "has_stopover": false,
      "google_link": "https://www.google.com/travel/flights?hl=tr&curr=TRY&gl=TR&q=IST%20to%20LAX%202026-06-26%202026-06-29",
      "scraped_at": "2026-06-05T22:29:14.162234",
      "data_source": "playwright_dom"
    },
    {
      "route": "IST-LAX",
      "origin": "IST",
      "dest": "LAX",
      "depart_date": "2026-08-14",
      "return_date": "2026-08-17",
      "price": 49144.0,
      "airline": "Çeşitli",
      "target": 20000,
      "alarm_threshold": 10000,
      "savings_pct": -146,
      "is_below_target": false,
      "is_mistake_fare": false,
      "has_stopover": false,
      "google_link": "https://www.google.com/travel/flights?hl=tr&curr=TRY&gl=TR&q=IST%20to%20LAX%202026-08-14%202026-08-17",
      "scraped_at": "2026-06-05T22:28:48.105557",
      "data_source": "playwright_dom"
    },
    {
      "route": "IST-LAX",
      "origin": "IST",
      "dest": "LAX",
      "depart_date": "2026-08-14",
      "return_date": "2026-08-17",
      "price": 52047.0,
      "airline": "Çeşitli",
      "target": 20000,
      "alarm_threshold": 10000,
      "savings_pct": -160,
      "is_below_target": false,
      "is_mistake_fare": false,
      "has_stopover": false,
      "google_link": "https://www.google.com/travel/flights?hl=tr&curr=TRY&gl=TR&q=IST%20to%20LAX%202026-08-14%202026-08-17",
      "scraped_at": "2026-06-05T22:28:48.105557",
      "data_source": "playwright_dom"
    },
    {
      "route": "IST-LAX",
      "origin": "IST",
      "dest": "LAX",
      "depart_date": "2026-08-14",
      "return_date": "2026-08-17",
      "price": 53011.0,
      "airline": "Çeşitli",
      "target": 20000,
      "alarm_threshold": 10000,
      "savings_pct": -165,
      "is_below_target": false,
      "is_mistake_fare": false,
      "has_stopover": false,
      "google_link": "https://www.google.com/travel/flights?hl=tr&curr=TRY&gl=TR&q=IST%20to%20LAX%202026-08-14%202026-08-17",
      "scraped_at": "2026-06-05T22:28:48.105557",
      "data_source": "playwright_dom"
    },
    {
      "route": "IST-LAX",
      "origin": "IST",
      "dest": "LAX",
      "depart_date": "2026-08-14",
      "return_date": "2026-08-17",
      "price": 53565.0,
      "airline": "Çeşitli",
      "target": 20000,
      "alarm_threshold": 10000,
      "savings_pct": -168,
      "is_below_target": false,
      "is_mistake_fare": false,
      "has_stopover": false,
      "google_link": "https://www.google.com/travel/flights?hl=tr&curr=TRY&gl=TR&q=IST%20to%20LAX%202026-08-14%202026-08-17",
      "scraped_at": "2026-06-05T22:28:48.105557",
      "data_source": "playwright_dom"
    },
    {
      "route": "IST-LAX",
      "origin": "IST",
      "dest": "LAX",
      "depart_date": "2026-08-14",
      "return_date": "2026-08-17",
      "price": 53826.0,
      "airline": "Çeşitli",
      "target": 20000,
      "alarm_threshold": 10000,
      "savings_pct": -169,
      "is_below_target": false,
      "is_mistake_fare": false,
      "has_stopover": false,
      "google_link": "https://www.google.com/travel/flights?hl=tr&curr=TRY&gl=TR&q=IST%20to%20LAX%202026-08-14%202026-08-17",
      "scraped_at": "2026-06-05T22:28:48.105557",
      "data_source": "playwright_dom"
    },
    {
      "route": "IST-LAX",
      "origin": "IST",
      "dest": "LAX",
      "depart_date": "2026-06-26",
      "return_date": "2026-06-29",
      "price": 56124.0,
      "airline": "Çeşitli",
      "target": 20000,
      "alarm_threshold": 10000,
      "savings_pct": -181,
      "is_below_target": false,
      "is_mistake_fare": false,
      "has_stopover": false,
      "google_link": "https://www.google.com/travel/flights?hl=tr&curr=TRY&gl=TR&q=IST%20to%20LAX%202026-06-26%202026-06-29",
      "scraped_at": "2026-06-05T22:29:14.162234",
      "data_source": "playwright_dom"
    },
    {
      "route": "IST-JFK",
      "origin": "IST",
      "dest": "JFK",
      "depart_date": "2026-08-14",
      "return_date": "2026-08-17",
      "price": 61870.0,
      "airline": "Çeşitli",
      "target": 18000,
      "alarm_threshold": 9000,
      "savings_pct": -244,
      "is_below_target": false,
      "is_mistake_fare": false,
      "has_stopover": false,
      "google_link": "https://www.google.com/travel/flights?hl=tr&curr=TRY&gl=TR&q=IST%20to%20JFK%202026-08-14%202026-08-17",
      "scraped_at": "2026-06-05T22:28:21.582931",
      "data_source": "playwright_dom"
    },
    {
      "route": "IST-JFK",
      "origin": "IST",
      "dest": "JFK",
      "depart_date": "2026-08-14",
      "return_date": "2026-08-17",
      "price": 62305.0,
      "airline": "Çeşitli",
      "target": 18000,
      "alarm_threshold": 9000,
      "savings_pct": -246,
      "is_below_target": false,
      "is_mistake_fare": false,
      "has_stopover": false,
      "google_link": "https://www.google.com/travel/flights?hl=tr&curr=TRY&gl=TR&q=IST%20to%20JFK%202026-08-14%202026-08-17",
      "scraped_at": "2026-06-05T22:28:21.582931",
      "data_source": "playwright_dom"
    },
    {
      "route": "IST-LAX",
      "origin": "IST",
      "dest": "LAX",
      "depart_date": "2026-08-14",
      "return_date": "2026-08-17",
      "price": 63249.0,
      "airline": "Çeşitli",
      "target": 20000,
      "alarm_threshold": 10000,
      "savings_pct": -216,
      "is_below_target": false,
      "is_mistake_fare": false,
      "has_stopover": false,
      "google_link": "https://www.google.com/travel/flights?hl=tr&curr=TRY&gl=TR&q=IST%20to%20LAX%202026-08-14%202026-08-17",
      "scraped_at": "2026-06-05T22:28:48.105557",
      "data_source": "playwright_dom"
    },
    {
      "route": "IST-JFK",
      "origin": "IST",
      "dest": "JFK",
      "depart_date": "2026-08-14",
      "return_date": "2026-08-17",
      "price": 64832.0,
      "airline": "Çeşitli",
      "target": 18000,
      "alarm_threshold": 9000,
      "savings_pct": -260,
      "is_below_target": false,
      "is_mistake_fare": false,
      "has_stopover": false,
      "google_link": "https://www.google.com/travel/flights?hl=tr&curr=TRY&gl=TR&q=IST%20to%20JFK%202026-08-14%202026-08-17",
      "scraped_at": "2026-06-05T22:28:21.582931",
      "data_source": "playwright_dom"
    },
    {
      "route": "IST-JFK",
      "origin": "IST",
      "dest": "JFK",
      "depart_date": "2026-08-14",
      "return_date": "2026-08-17",
      "price": 66440.0,
      "airline": "Çeşitli",
      "target": 18000,
      "alarm_threshold": 9000,
      "savings_pct": -269,
      "is_below_target": false,
      "is_mistake_fare": false,
      "has_stopover": false,
      "google_link": "https://www.google.com/travel/flights?hl=tr&curr=TRY&gl=TR&q=IST%20to%20JFK%202026-08-14%202026-08-17",
      "scraped_at": "2026-06-05T22:28:21.582931",
      "data_source": "playwright_dom"
    },
    {
      "route": "IST-LAX",
      "origin": "IST",
      "dest": "LAX",
      "depart_date": "2026-06-26",
      "return_date": "2026-06-29",
      "price": 67846.0,
      "airline": "Çeşitli",
      "target": 20000,
      "alarm_threshold": 10000,
      "savings_pct": -239,
      "is_below_target": false,
      "is_mistake_fare": false,
      "has_stopover": false,
      "google_link": "https://www.google.com/travel/flights?hl=tr&curr=TRY&gl=TR&q=IST%20to%20LAX%202026-06-26%202026-06-29",
      "scraped_at": "2026-06-05T22:29:14.162234",
      "data_source": "playwright_dom"
    }
  ]
}