{
  "last_updated": "2026-05-09T22:08:43.471007",
  "total_found": 121,
  "below_target": 3,
  "alarms_sent_this_run": 1,
  "direct_threshold_pct": 50,
  "stopover_threshold_pct": 90,
  "data_source": "playwright_chromium",
  "flights": [
    {
      "route": "IST-LHR",
      "origin": "IST",
      "dest": "LHR",
      "depart_date": "2026-08-07",
      "return_date": "2026-08-10",
      "price": 1000.0,
      "airline": "Çeşitli",
      "target": 3200,
      "alarm_threshold": 1600,
      "savings_pct": 69,
      "is_below_target": false,
      "is_mistake_fare": true,
      "has_stopover": true,
      "google_link": "https://www.google.com/travel/flights?hl=tr&curr=TRY&gl=TR&q=IST%20to%20LHR%202026-08-07%202026-08-10",
      "scraped_at": "2026-05-09T21:50:01.948060",
      "data_source": "url_html"
    },
    {
      "route": "IST-LHR",
      "origin": "IST",
      "dest": "LHR",
      "depart_date": "2026-08-21",
      "return_date": "2026-08-24",
      "price": 1000.0,
      "airline": "Çeşitli",
      "target": 3200,
      "alarm_threshold": 1600,
      "savings_pct": 69,
      "is_below_target": false,
      "is_mistake_fare": true,
      "has_stopover": true,
      "google_link": "https://www.google.com/travel/flights?hl=tr&curr=TRY&gl=TR&q=IST%20to%20LHR%202026-08-21%202026-08-24",
      "scraped_at": "2026-05-09T21:50:32.996602",
      "data_source": "url_html"
    },
    {
      "route": "IST-AMS",
      "origin": "IST",
      "dest": "AMS",
      "depart_date": "2026-06-05",
      "return_date": "2026-06-08",
      "price": 1000.0,
      "airline": "Çeşitli",
      "target": 2800,
      "alarm_threshold": 1400,
      "savings_pct": 64,
      "is_below_target": false,
      "is_mistake_fare": true,
      "has_stopover": true,
      "google_link": "https://www.google.com/travel/flights?hl=tr&curr=TRY&gl=TR&q=IST%20to%20AMS%202026-06-05%202026-06-08",
      "scraped_at": "2026-05-09T21:51:43.777162",
      "data_source": "url_html"
    },
    {
      "route": "IST-BCN",
      "origin": "IST",
      "dest": "BCN",
      "depart_date": "2026-06-12",
      "return_date": "2026-06-15",
      "price": 1000.0,
      "airline": "Çeşitli",
      "target": 2900,
      "alarm_threshold": 1450,
      "savings_pct": 66,
      "is_below_target": false,
      "is_mistake_fare": true,
      "has_stopover": true,
      "google_link": "https://www.google.com/travel/flights?hl=tr&curr=TRY&gl=TR&q=IST%20to%20BCN%202026-06-12%202026-06-15",
      "scraped_at": "2026-05-09T21:52:35.724591",
      "data_source": "url_html"
    },
    {
      "route": "IST-FCO",
      "origin": "IST",
      "dest": "FCO",
      "depart_date": "2026-08-21",
      "return_date": "2026-08-24",
      "price": 1000.0,
      "airline": "Çeşitli",
      "target": 2600,
      "alarm_threshold": 1300,
      "savings_pct": 62,
      "is_below_target": false,
      "is_mistake_fare": true,
      "has_stopover": true,
      "google_link": "https://www.google.com/travel/flights?hl=tr&curr=TRY&gl=TR&q=IST%20to%20FCO%202026-08-21%202026-08-24",
      "scraped_at": "2026-05-09T21:53:33.907658",
      "data_source": "url_html"
    },
    {
      "route": "IST-MAD",
      "origin": "IST",
      "dest": "MAD",
      "depart_date": "2026-08-21",
      "return_date": "2026-08-24",
      "price": 1000.0,
      "airline": "Çeşitli",
      "target": 3100,
      "alarm_threshold": 1550,
      "savings_pct": 68,
      "is_below_target": false,
      "is_mistake_fare": true,
      "has_stopover": true,
      "google_link": "https://www.google.com/travel/flights?hl=tr&curr=TRY&gl=TR&q=IST%20to%20MAD%202026-08-21%202026-08-24",
      "scraped_at": "2026-05-09T21:54:03.083484",
      "data_source": "url_html"
    },
    {
      "route": "IST-FRA",
      "origin": "IST",
      "dest": "FRA",
      "depart_date": "2026-06-05",
      "return_date": "2026-06-08",
      "price": 1000.0,
      "airline": "Çeşitli",
      "target": 2700,
      "alarm_threshold": 1350,
      "savings_pct": 63,
      "is_below_target": false,
      "is_mistake_fare": true,
      "has_stopover": true,
      "google_link": "https://www.google.com/travel/flights?hl=tr&curr=TRY&gl=TR&q=IST%20to%20FRA%202026-06-05%202026-06-08",
      "scraped_at": "2026-05-09T21:55:17.776328",
      "data_source": "url_html"
    },
    {
      "route": "IST-MUC",
      "origin": "IST",
      "dest": "MUC",
      "depart_date": "2026-06-05",
      "return_date": "2026-06-08",
      "price": 1000.0,
      "airline": "Çeşitli",
      "target": 2500,
      "alarm_threshold": 1250,
      "savings_pct": 60,
      "is_below_target": false,
      "is_mistake_fare": true,
      "has_stopover": true,
      "google_link": "https://www.google.com/travel/flights?hl=tr&curr=TRY&gl=TR&q=IST%20to%20MUC%202026-06-05%202026-06-08",
      "scraped_at": "2026-05-09T21:56:57.737385",
      "data_source": "url_html"
    },
    {
      "route": "IST-VIE",
      "origin": "IST",
      "dest": "VIE",
      "depart_date": "2026-08-21",
      "return_date": "2026-08-24",
      "price": 1000.0,
      "airline": "Çeşitli",
      "target": 2400,
      "alarm_threshold": 1200,
      "savings_pct": 58,
      "is_below_target": false,
      "is_mistake_fare": true,
      "has_stopover": true,
      "google_link": "https://www.google.com/travel/flights?hl=tr&curr=TRY&gl=TR&q=IST%20to%20VIE%202026-08-21%202026-08-24",
      "scraped_at": "2026-05-09T21:57:57.742340",
      "data_source": "url_html"
    },
    {
      "route": "IST-DXB",
      "origin": "IST",
      "dest": "DXB",
      "depart_date": "2026-06-12",
      "return_date": "2026-06-15",
      "price": 1000.0,
      "airline": "Çeşitli",
      "target": 2200,
      "alarm_threshold": 1100,
      "savings_pct": 55,
      "is_below_target": false,
      "is_mistake_fare": true,
      "has_stopover": true,
      "google_link": "https://www.google.com/travel/flights?hl=tr&curr=TRY&gl=TR&q=IST%20to%20DXB%202026-06-12%202026-06-15",
      "scraped_at": "2026-05-09T22:00:24.539315",
      "data_source": "url_html"
    },
    {
      "route": "IST-DXB",
      "origin": "IST",
      "dest": "DXB",
      "depart_date": "2026-08-21",
      "return_date": "2026-08-24",
      "price": 1000.0,
      "airline": "Çeşitli",
      "target": 2200,
      "alarm_threshold": 1100,
      "savings_pct": 55,
      "is_below_target": false,
      "is_mistake_fare": true,
      "has_stopover": true,
      "google_link": "https://www.google.com/travel/flights?hl=tr&curr=TRY&gl=TR&q=IST%20to%20DXB%202026-08-21%202026-08-24",
      "scraped_at": "2026-05-09T22:00:53.393761",
      "data_source": "url_html"
    },
    {
      "route": "IST-JFK",
      "origin": "IST",
      "dest": "JFK",
      "depart_date": "2026-07-10",
      "return_date": "2026-07-13",
      "price": 1000.0,
      "airline": "Çeşitli",
      "target": 18000,
      "alarm_threshold": 9000,
      "savings_pct": 94,
      "is_below_target": true,
      "is_mistake_fare": true,
      "has_stopover": true,
      "google_link": "https://www.google.com/travel/flights?hl=tr&curr=TRY&gl=TR&q=IST%20to%20JFK%202026-07-10%202026-07-13",
      "scraped_at": "2026-05-09T22:01:24.103705",
      "data_source": "url_html"
    },
    {
      "route": "IST-JFK",
      "origin": "IST",
      "dest": "JFK",
      "depart_date": "2026-06-05",
      "return_date": "2026-06-08",
      "price": 1000.0,
      "airline": "Çeşitli",
      "target": 18000,
      "alarm_threshold": 9000,
      "savings_pct": 94,
      "is_below_target": true,
      "is_mistake_fare": true,
      "has_stopover": true,
      "google_link": "https://www.google.com/travel/flights?hl=tr&curr=TRY&gl=TR&q=IST%20to%20JFK%202026-06-05%202026-06-08",
      "scraped_at": "2026-05-09T22:02:01.888887",
      "data_source": "url_html"
    },
    {
      "route": "IST-LAX",
      "origin": "IST",
      "dest": "LAX",
      "depart_date": "2026-08-07",
      "return_date": "2026-08-10",
      "price": 1000.0,
      "airline": "Çeşitli",
      "target": 20000,
      "alarm_threshold": 10000,
      "savings_pct": 95,
      "is_below_target": true,
      "is_mistake_fare": true,
      "has_stopover": true,
      "google_link": "https://www.google.com/travel/flights?hl=tr&curr=TRY&gl=TR&q=IST%20to%20LAX%202026-08-07%202026-08-10",
      "scraped_at": "2026-05-09T22:02:44.434044",
      "data_source": "url_html"
    },
    {
      "route": "SAW-CDG",
      "origin": "SAW",
      "dest": "CDG",
      "depart_date": "2026-09-04",
      "return_date": "2026-09-07",
      "price": 1000.0,
      "airline": "Çeşitli",
      "target": 2800,
      "alarm_threshold": 1400,
      "savings_pct": 64,
      "is_below_target": false,
      "is_mistake_fare": true,
      "has_stopover": true,
      "google_link": "https://www.google.com/travel/flights?hl=tr&curr=TRY&gl=TR&q=SAW%20to%20CDG%202026-09-04%202026-09-07",
      "scraped_at": "2026-05-09T22:03:42.368844",
      "data_source": "url_html"
    },
    {
      "route": "SAW-LHR",
      "origin": "SAW",
      "dest": "LHR",
      "depart_date": "2026-07-24",
      "return_date": "2026-07-27",
      "price": 1000.0,
      "airline": "Çeşitli",
      "target": 3000,
      "alarm_threshold": 1500,
      "savings_pct": 67,
      "is_below_target": false,
      "is_mistake_fare": true,
      "has_stopover": true,
      "google_link": "https://www.google.com/travel/flights?hl=tr&curr=TRY&gl=TR&q=SAW%20to%20LHR%202026-07-24%202026-07-27",
      "scraped_at": "2026-05-09T22:04:36.406096",
      "data_source": "url_html"
    },
    {
      "route": "SAW-LHR",
      "origin": "SAW",
      "dest": "LHR",
      "depart_date": "2026-06-19",
      "return_date": "2026-06-22",
      "price": 1000.0,
      "airline": "Çeşitli",
      "target": 3000,
      "alarm_threshold": 1500,
      "savings_pct": 67,
      "is_below_target": false,
      "is_mistake_fare": true,
      "has_stopover": true,
      "google_link": "https://www.google.com/travel/flights?hl=tr&curr=TRY&gl=TR&q=SAW%20to%20LHR%202026-06-19%202026-06-22",
      "scraped_at": "2026-05-09T22:05:09.595973",
      "data_source": "url_html"
    },
    {
      "route": "SAW-AMS",
      "origin": "SAW",
      "dest": "AMS",
      "depart_date": "2026-08-07",
      "return_date": "2026-08-10",
      "price": 1000.0,
      "airline": "Çeşitli",
      "target": 2600,
      "alarm_threshold": 1300,
      "savings_pct": 62,
      "is_below_target": false,
      "is_mistake_fare": true,
      "has_stopover": true,
      "google_link": "https://www.google.com/travel/flights?hl=tr&curr=TRY&gl=TR&q=SAW%20to%20AMS%202026-08-07%202026-08-10",
      "scraped_at": "2026-05-09T22:05:52.918076",
      "data_source": "url_html"
    },
    {
      "route": "SAW-AMS",
      "origin": "SAW",
      "dest": "AMS",
      "depart_date": "2026-08-21",
      "return_date": "2026-08-24",
      "price": 1000.0,
      "airline": "Çeşitli",
      "target": 2600,
      "alarm_threshold": 1300,
      "savings_pct": 62,
      "is_below_target": false,
      "is_mistake_fare": true,
      "has_stopover": true,
      "google_link": "https://www.google.com/travel/flights?hl=tr&curr=TRY&gl=TR&q=SAW%20to%20AMS%202026-08-21%202026-08-24",
      "scraped_at": "2026-05-09T22:06:24.820901",
      "data_source": "url_html"
    },
    {
      "route": "SAW-BCN",
      "origin": "SAW",
      "dest": "BCN",
      "depart_date": "2026-09-04",
      "return_date": "2026-09-07",
      "price": 1000.0,
      "airline": "Çeşitli",
      "target": 2700,
      "alarm_threshold": 1350,
      "savings_pct": 63,
      "is_below_target": false,
      "is_mistake_fare": true,
      "has_stopover": true,
      "google_link": "https://www.google.com/travel/flights?hl=tr&curr=TRY&gl=TR&q=SAW%20to%20BCN%202026-09-04%202026-09-07",
      "scraped_at": "2026-05-09T22:06:50.517718",
      "data_source": "url_html"
    },
    {
      "route": "SAW-BCN",
      "origin": "SAW",
      "dest": "BCN",
      "depart_date": "2026-07-10",
      "return_date": "2026-07-13",
      "price": 1000.0,
      "airline": "Çeşitli",
      "target": 2700,
      "alarm_threshold": 1350,
      "savings_pct": 63,
      "is_below_target": false,
      "is_mistake_fare": true,
      "has_stopover": true,
      "google_link": "https://www.google.com/travel/flights?hl=tr&curr=TRY&gl=TR&q=SAW%20to%20BCN%202026-07-10%202026-07-13",
      "scraped_at": "2026-05-09T22:07:17.321100",
      "data_source": "url_html"
    },
    {
      "route": "SAW-FCO",
      "origin": "SAW",
      "dest": "FCO",
      "depart_date": "2026-08-07",
      "return_date": "2026-08-10",
      "price": 1000.0,
      "airline": "Çeşitli",
      "target": 2400,
      "alarm_threshold": 1200,
      "savings_pct": 58,
      "is_below_target": false,
      "is_mistake_fare": true,
      "has_stopover": true,
      "google_link": "https://www.google.com/travel/flights?hl=tr&curr=TRY&gl=TR&q=SAW%20to%20FCO%202026-08-07%202026-08-10",
      "scraped_at": "2026-05-09T22:07:58.293815",
      "data_source": "url_html"
    },
    {
      "route": "SAW-FCO",
      "origin": "SAW",
      "dest": "FCO",
      "depart_date": "2026-06-12",
      "return_date": "2026-06-15",
      "price": 1000.0,
      "airline": "Çeşitli",
      "target": 2400,
      "alarm_threshold": 1200,
      "savings_pct": 58,
      "is_below_target": false,
      "is_mistake_fare": true,
      "has_stopover": true,
      "google_link": "https://www.google.com/travel/flights?hl=tr&curr=TRY&gl=TR&q=SAW%20to%20FCO%202026-06-12%202026-06-15",
      "scraped_at": "2026-05-09T22:08:29.974145",
      "data_source": "url_html"
    },
    {
      "route": "IST-FCO",
      "origin": "IST",
      "dest": "FCO",
      "depart_date": "2026-08-21",
      "return_date": "2026-08-24",
      "price": 1060.0,
      "airline": "Çeşitli",
      "target": 2600,
      "alarm_threshold": 1300,
      "savings_pct": 59,
      "is_below_target": false,
      "is_mistake_fare": true,
      "has_stopover": true,
      "google_link": "https://www.google.com/travel/flights?hl=tr&curr=TRY&gl=TR&q=IST%20to%20FCO%202026-08-21%202026-08-24",
      "scraped_at": "2026-05-09T21:53:33.907658",
      "data_source": "url_html"
    },
    {
      "route": "IST-VIE",
      "origin": "IST",
      "dest": "VIE",
      "depart_date": "2026-08-21",
      "return_date": "2026-08-24",
      "price": 1095.0,
      "airline": "Çeşitli",
      "target": 2400,
      "alarm_threshold": 1200,
      "savings_pct": 54,
      "is_below_target": false,
      "is_mistake_fare": true,
      "has_stopover": true,
      "google_link": "https://www.google.com/travel/flights?hl=tr&curr=TRY&gl=TR&q=IST%20to%20VIE%202026-08-21%202026-08-24",
      "scraped_at": "2026-05-09T21:57:57.742340",
      "data_source": "url_html"
    },
    {
      "route": "SAW-CDG",
      "origin": "SAW",
      "dest": "CDG",
      "depart_date": "2026-09-04",
      "return_date": "2026-09-07",
      "price": 1120.0,
      "airline": "Çeşitli",
      "target": 2800,
      "alarm_threshold": 1400,
      "savings_pct": 60,
      "is_below_target": false,
      "is_mistake_fare": true,
      "has_stopover": true,
      "google_link": "https://www.google.com/travel/flights?hl=tr&curr=TRY&gl=TR&q=SAW%20to%20CDG%202026-09-04%202026-09-07",
      "scraped_at": "2026-05-09T22:03:42.368844",
      "data_source": "url_html"
    },
    {
      "route": "IST-DXB",
      "origin": "IST",
      "dest": "DXB",
      "depart_date": "2026-08-21",
      "return_date": "2026-08-24",
      "price": 1295.0,
      "airline": "Çeşitli",
      "target": 2200,
      "alarm_threshold": 1100,
      "savings_pct": 41,
      "is_below_target": false,
      "is_mistake_fare": true,
      "has_stopover": true,
      "google_link": "https://www.google.com/travel/flights?hl=tr&curr=TRY&gl=TR&q=IST%20to%20DXB%202026-08-21%202026-08-24",
      "scraped_at": "2026-05-09T22:00:53.393761",
      "data_source": "url_html"
    },
    {
      "route": "IST-MUC",
      "origin": "IST",
      "dest": "MUC",
      "depart_date": "2026-06-05",
      "return_date": "2026-06-08",
      "price": 1380.0,
      "airline": "Çeşitli",
      "target": 2500,
      "alarm_threshold": 1250,
      "savings_pct": 45,
      "is_below_target": false,
      "is_mistake_fare": true,
      "has_stopover": true,
      "google_link": "https://www.google.com/travel/flights?hl=tr&curr=TRY&gl=TR&q=IST%20to%20MUC%202026-06-05%202026-06-08",
      "scraped_at": "2026-05-09T21:56:57.737385",
      "data_source": "url_html"
    },
    {
      "route": "SAW-LHR",
      "origin": "SAW",
      "dest": "LHR",
      "depart_date": "2026-07-24",
      "return_date": "2026-07-27",
      "price": 1420.0,
      "airline": "Çeşitli",
      "target": 3000,
      "alarm_threshold": 1500,
      "savings_pct": 53,
      "is_below_target": false,
      "is_mistake_fare": true,
      "has_stopover": true,
      "google_link": "https://www.google.com/travel/flights?hl=tr&curr=TRY&gl=TR&q=SAW%20to%20LHR%202026-07-24%202026-07-27",
      "scraped_at": "2026-05-09T22:04:36.406096",
      "data_source": "url_html"
    },
    {
      "route": "SAW-LHR",
      "origin": "SAW",
      "dest": "LHR",
      "depart_date": "2026-06-19",
      "return_date": "2026-06-22",
      "price": 1420.0,
      "airline": "Çeşitli",
      "target": 3000,
      "alarm_threshold": 1500,
      "savings_pct": 53,
      "is_below_target": false,
      "is_mistake_fare": true,
      "has_stopover": true,
      "google_link": "https://www.google.com/travel/flights?hl=tr&curr=TRY&gl=TR&q=SAW%20to%20LHR%202026-06-19%202026-06-22",
      "scraped_at": "2026-05-09T22:05:09.595973",
      "data_source": "url_html"
    },
    {
      "route": "IST-BCN",
      "origin": "IST",
      "dest": "BCN",
      "depart_date": "2026-06-12",
      "return_date": "2026-06-15",
      "price": 2605.0,
      "airline": "Çeşitli",
      "target": 2900,
      "alarm_threshold": 1450,
      "savings_pct": 10,
      "is_below_target": false,
      "is_mistake_fare": true,
      "has_stopover": true,
      "google_link": "https://www.google.com/travel/flights?hl=tr&curr=TRY&gl=TR&q=IST%20to%20BCN%202026-06-12%202026-06-15",
      "scraped_at": "2026-05-09T21:52:35.724591",
      "data_source": "url_html"
    },
    {
      "route": "IST-DXB",
      "origin": "IST",
      "dest": "DXB",
      "depart_date": "2026-06-12",
      "return_date": "2026-06-15",
      "price": 2605.0,
      "airline": "Çeşitli",
      "target": 2200,
      "alarm_threshold": 1100,
      "savings_pct": -18,
      "is_below_target": false,
      "is_mistake_fare": true,
      "has_stopover": true,
      "google_link": "https://www.google.com/travel/flights?hl=tr&curr=TRY&gl=TR&q=IST%20to%20DXB%202026-06-12%202026-06-15",
      "scraped_at": "2026-05-09T22:00:24.539315",
      "data_source": "url_html"
    },
    {
      "route": "IST-JFK",
      "origin": "IST",
      "dest": "JFK",
      "depart_date": "2026-07-10",
      "return_date": "2026-07-13",
      "price": 2605.0,
      "airline": "Çeşitli",
      "target": 18000,
      "alarm_threshold": 9000,
      "savings_pct": 86,
      "is_below_target": false,
      "is_mistake_fare": true,
      "has_stopover": true,
      "google_link": "https://www.google.com/travel/flights?hl=tr&curr=TRY&gl=TR&q=IST%20to%20JFK%202026-07-10%202026-07-13",
      "scraped_at": "2026-05-09T22:01:24.103705",
      "data_source": "url_html"
    },
    {
      "route": "SAW-BCN",
      "origin": "SAW",
      "dest": "BCN",
      "depart_date": "2026-07-10",
      "return_date": "2026-07-13",
      "price": 2605.0,
      "airline": "Çeşitli",
      "target": 2700,
      "alarm_threshold": 1350,
      "savings_pct": 4,
      "is_below_target": false,
      "is_mistake_fare": true,
      "has_stopover": true,
      "google_link": "https://www.google.com/travel/flights?hl=tr&curr=TRY&gl=TR&q=SAW%20to%20BCN%202026-07-10%202026-07-13",
      "scraped_at": "2026-05-09T22:07:17.321100",
      "data_source": "url_html"
    },
    {
      "route": "SAW-FCO",
      "origin": "SAW",
      "dest": "FCO",
      "depart_date": "2026-06-12",
      "return_date": "2026-06-15",
      "price": 2605.0,
      "airline": "Çeşitli",
      "target": 2400,
      "alarm_threshold": 1200,
      "savings_pct": -9,
      "is_below_target": false,
      "is_mistake_fare": true,
      "has_stopover": true,
      "google_link": "https://www.google.com/travel/flights?hl=tr&curr=TRY&gl=TR&q=SAW%20to%20FCO%202026-06-12%202026-06-15",
      "scraped_at": "2026-05-09T22:08:29.974145",
      "data_source": "url_html"
    },
    {
      "route": "IST-BCN",
      "origin": "IST",
      "dest": "BCN",
      "depart_date": "2026-06-12",
      "return_date": "2026-06-15",
      "price": 2808.0,
      "airline": "Çeşitli",
      "target": 2900,
      "alarm_threshold": 1450,
      "savings_pct": 3,
      "is_below_target": false,
      "is_mistake_fare": true,
      "has_stopover": true,
      "google_link": "https://www.google.com/travel/flights?hl=tr&curr=TRY&gl=TR&q=IST%20to%20BCN%202026-06-12%202026-06-15",
      "scraped_at": "2026-05-09T21:52:35.724591",
      "data_source": "url_html"
    },
    {
      "route": "IST-DXB",
      "origin": "IST",
      "dest": "DXB",
      "depart_date": "2026-06-12",
      "return_date": "2026-06-15",
      "price": 2808.0,
      "airline": "Çeşitli",
      "target": 2200,
      "alarm_threshold": 1100,
      "savings_pct": -28,
      "is_below_target": false,
      "is_mistake_fare": true,
      "has_stopover": true,
      "google_link": "https://www.google.com/travel/flights?hl=tr&curr=TRY&gl=TR&q=IST%20to%20DXB%202026-06-12%202026-06-15",
      "scraped_at": "2026-05-09T22:00:24.539315",
      "data_source": "url_html"
    },
    {
      "route": "IST-JFK",
      "origin": "IST",
      "dest": "JFK",
      "depart_date": "2026-07-10",
      "return_date": "2026-07-13",
      "price": 2808.0,
      "airline": "Çeşitli",
      "target": 18000,
      "alarm_threshold": 9000,
      "savings_pct": 84,
      "is_below_target": false,
      "is_mistake_fare": true,
      "has_stopover": true,
      "google_link": "https://www.google.com/travel/flights?hl=tr&curr=TRY&gl=TR&q=IST%20to%20JFK%202026-07-10%202026-07-13",
      "scraped_at": "2026-05-09T22:01:24.103705",
      "data_source": "url_html"
    },
    {
      "route": "SAW-BCN",
      "origin": "SAW",
      "dest": "BCN",
      "depart_date": "2026-07-10",
      "return_date": "2026-07-13",
      "price": 2808.0,
      "airline": "Çeşitli",
      "target": 2700,
      "alarm_threshold": 1350,
      "savings_pct": -4,
      "is_below_target": false,
      "is_mistake_fare": true,
      "has_stopover": true,
      "google_link": "https://www.google.com/travel/flights?hl=tr&curr=TRY&gl=TR&q=SAW%20to%20BCN%202026-07-10%202026-07-13",
      "scraped_at": "2026-05-09T22:07:17.321100",
      "data_source": "url_html"
    },
    {
      "route": "SAW-FCO",
      "origin": "SAW",
      "dest": "FCO",
      "depart_date": "2026-06-12",
      "return_date": "2026-06-15",
      "price": 2808.0,
      "airline": "Çeşitli",
      "target": 2400,
      "alarm_threshold": 1200,
      "savings_pct": -17,
      "is_below_target": false,
      "is_mistake_fare": true,
      "has_stopover": true,
      "google_link": "https://www.google.com/travel/flights?hl=tr&curr=TRY&gl=TR&q=SAW%20to%20FCO%202026-06-12%202026-06-15",
      "scraped_at": "2026-05-09T22:08:29.974145",
      "data_source": "url_html"
    },
    {
      "route": "IST-BCN",
      "origin": "IST",
      "dest": "BCN",
      "depart_date": "2026-06-12",
      "return_date": "2026-06-15",
      "price": 3082.0,
      "airline": "Çeşitli",
      "target": 2900,
      "alarm_threshold": 1450,
      "savings_pct": -6,
      "is_below_target": false,
      "is_mistake_fare": true,
      "has_stopover": true,
      "google_link": "https://www.google.com/travel/flights?hl=tr&curr=TRY&gl=TR&q=IST%20to%20BCN%202026-06-12%202026-06-15",
      "scraped_at": "2026-05-09T21:52:35.724591",
      "data_source": "url_html"
    },
    {
      "route": "IST-DXB",
      "origin": "IST",
      "dest": "DXB",
      "depart_date": "2026-06-12",
      "return_date": "2026-06-15",
      "price": 3082.0,
      "airline": "Çeşitli",
      "target": 2200,
      "alarm_threshold": 1100,
      "savings_pct": -40,
      "is_below_target": false,
      "is_mistake_fare": true,
      "has_stopover": true,
      "google_link": "https://www.google.com/travel/flights?hl=tr&curr=TRY&gl=TR&q=IST%20to%20DXB%202026-06-12%202026-06-15",
      "scraped_at": "2026-05-09T22:00:24.539315",
      "data_source": "url_html"
    },
    {
      "route": "IST-JFK",
      "origin": "IST",
      "dest": "JFK",
      "depart_date": "2026-07-10",
      "return_date": "2026-07-13",
      "price": 3082.0,
      "airline": "Çeşitli",
      "target": 18000,
      "alarm_threshold": 9000,
      "savings_pct": 83,
      "is_below_target": false,
      "is_mistake_fare": true,
      "has_stopover": true,
      "google_link": "https://www.google.com/travel/flights?hl=tr&curr=TRY&gl=TR&q=IST%20to%20JFK%202026-07-10%202026-07-13",
      "scraped_at": "2026-05-09T22:01:24.103705",
      "data_source": "url_html"
    },
    {
      "route": "SAW-BCN",
      "origin": "SAW",
      "dest": "BCN",
      "depart_date": "2026-07-10",
      "return_date": "2026-07-13",
      "price": 3082.0,
      "airline": "Çeşitli",
      "target": 2700,
      "alarm_threshold": 1350,
      "savings_pct": -14,
      "is_below_target": false,
      "is_mistake_fare": true,
      "has_stopover": true,
      "google_link": "https://www.google.com/travel/flights?hl=tr&curr=TRY&gl=TR&q=SAW%20to%20BCN%202026-07-10%202026-07-13",
      "scraped_at": "2026-05-09T22:07:17.321100",
      "data_source": "url_html"
    },
    {
      "route": "SAW-FCO",
      "origin": "SAW",
      "dest": "FCO",
      "depart_date": "2026-06-12",
      "return_date": "2026-06-15",
      "price": 3082.0,
      "airline": "Çeşitli",
      "target": 2400,
      "alarm_threshold": 1200,
      "savings_pct": -28,
      "is_below_target": false,
      "is_mistake_fare": true,
      "has_stopover": true,
      "google_link": "https://www.google.com/travel/flights?hl=tr&curr=TRY&gl=TR&q=SAW%20to%20FCO%202026-06-12%202026-06-15",
      "scraped_at": "2026-05-09T22:08:29.974145",
      "data_source": "url_html"
    },
    {
      "route": "IST-BCN",
      "origin": "IST",
      "dest": "BCN",
      "depart_date": "2026-06-12",
      "return_date": "2026-06-15",
      "price": 3366.0,
      "airline": "Çeşitli",
      "target": 2900,
      "alarm_threshold": 1450,
      "savings_pct": -16,
      "is_below_target": false,
      "is_mistake_fare": true,
      "has_stopover": true,
      "google_link": "https://www.google.com/travel/flights?hl=tr&curr=TRY&gl=TR&q=IST%20to%20BCN%202026-06-12%202026-06-15",
      "scraped_at": "2026-05-09T21:52:35.724591",
      "data_source": "url_html"
    },
    {
      "route": "IST-DXB",
      "origin": "IST",
      "dest": "DXB",
      "depart_date": "2026-06-12",
      "return_date": "2026-06-15",
      "price": 3366.0,
      "airline": "Çeşitli",
      "target": 2200,
      "alarm_threshold": 1100,
      "savings_pct": -53,
      "is_below_target": false,
      "is_mistake_fare": true,
      "has_stopover": true,
      "google_link": "https://www.google.com/travel/flights?hl=tr&curr=TRY&gl=TR&q=IST%20to%20DXB%202026-06-12%202026-06-15",
      "scraped_at": "2026-05-09T22:00:24.539315",
      "data_source": "url_html"
    },
    {
      "route": "IST-JFK",
      "origin": "IST",
      "dest": "JFK",
      "depart_date": "2026-07-10",
      "return_date": "2026-07-13",
      "price": 3366.0,
      "airline": "Çeşitli",
      "target": 18000,
      "alarm_threshold": 9000,
      "savings_pct": 81,
      "is_below_target": false,
      "is_mistake_fare": true,
      "has_stopover": true,
      "google_link": "https://www.google.com/travel/flights?hl=tr&curr=TRY&gl=TR&q=IST%20to%20JFK%202026-07-10%202026-07-13",
      "scraped_at": "2026-05-09T22:01:24.103705",
      "data_source": "url_html"
    },
    {
      "route": "SAW-BCN",
      "origin": "SAW",
      "dest": "BCN",
      "depart_date": "2026-07-10",
      "return_date": "2026-07-13",
      "price": 3366.0,
      "airline": "Çeşitli",
      "target": 2700,
      "alarm_threshold": 1350,
      "savings_pct": -25,
      "is_below_target": false,
      "is_mistake_fare": true,
      "has_stopover": true,
      "google_link": "https://www.google.com/travel/flights?hl=tr&curr=TRY&gl=TR&q=SAW%20to%20BCN%202026-07-10%202026-07-13",
      "scraped_at": "2026-05-09T22:07:17.321100",
      "data_source": "url_html"
    },
    {
      "route": "SAW-FCO",
      "origin": "SAW",
      "dest": "FCO",
      "depart_date": "2026-06-12",
      "return_date": "2026-06-15",
      "price": 3366.0,
      "airline": "Çeşitli",
      "target": 2400,
      "alarm_threshold": 1200,
      "savings_pct": -40,
      "is_below_target": false,
      "is_mistake_fare": true,
      "has_stopover": true,
      "google_link": "https://www.google.com/travel/flights?hl=tr&curr=TRY&gl=TR&q=SAW%20to%20FCO%202026-06-12%202026-06-15",
      "scraped_at": "2026-05-09T22:08:29.974145",
      "data_source": "url_html"
    },
    {
      "route": "IST-LHR",
      "origin": "IST",
      "dest": "LHR",
      "depart_date": "2026-08-07",
      "return_date": "2026-08-10",
      "price": 8000.0,
      "airline": "Çeşitli",
      "target": 3200,
      "alarm_threshold": 1600,
      "savings_pct": -150,
      "is_below_target": false,
      "is_mistake_fare": true,
      "has_stopover": true,
      "google_link": "https://www.google.com/travel/flights?hl=tr&curr=TRY&gl=TR&q=IST%20to%20LHR%202026-08-07%202026-08-10",
      "scraped_at": "2026-05-09T21:50:01.948060",
      "data_source": "url_html"
    },
    {
      "route": "IST-LHR",
      "origin": "IST",
      "dest": "LHR",
      "depart_date": "2026-08-21",
      "return_date": "2026-08-24",
      "price": 8000.0,
      "airline": "Çeşitli",
      "target": 3200,
      "alarm_threshold": 1600,
      "savings_pct": -150,
      "is_below_target": false,
      "is_mistake_fare": true,
      "has_stopover": true,
      "google_link": "https://www.google.com/travel/flights?hl=tr&curr=TRY&gl=TR&q=IST%20to%20LHR%202026-08-21%202026-08-24",
      "scraped_at": "2026-05-09T21:50:32.996602",
      "data_source": "url_html"
    },
    {
      "route": "IST-AMS",
      "origin": "IST",
      "dest": "AMS",
      "depart_date": "2026-06-05",
      "return_date": "2026-06-08",
      "price": 8000.0,
      "airline": "Çeşitli",
      "target": 2800,
      "alarm_threshold": 1400,
      "savings_pct": -186,
      "is_below_target": false,
      "is_mistake_fare": true,
      "has_stopover": true,
      "google_link": "https://www.google.com/travel/flights?hl=tr&curr=TRY&gl=TR&q=IST%20to%20AMS%202026-06-05%202026-06-08",
      "scraped_at": "2026-05-09T21:51:43.777162",
      "data_source": "url_html"
    },
    {
      "route": "IST-FCO",
      "origin": "IST",
      "dest": "FCO",
      "depart_date": "2026-08-21",
      "return_date": "2026-08-24",
      "price": 8000.0,
      "airline": "Çeşitli",
      "target": 2600,
      "alarm_threshold": 1300,
      "savings_pct": -208,
      "is_below_target": false,
      "is_mistake_fare": true,
      "has_stopover": true,
      "google_link": "https://www.google.com/travel/flights?hl=tr&curr=TRY&gl=TR&q=IST%20to%20FCO%202026-08-21%202026-08-24",
      "scraped_at": "2026-05-09T21:53:33.907658",
      "data_source": "url_html"
    },
    {
      "route": "IST-MAD",
      "origin": "IST",
      "dest": "MAD",
      "depart_date": "2026-08-21",
      "return_date": "2026-08-24",
      "price": 8000.0,
      "airline": "Çeşitli",
      "target": 3100,
      "alarm_threshold": 1550,
      "savings_pct": -158,
      "is_below_target": false,
      "is_mistake_fare": true,
      "has_stopover": true,
      "google_link": "https://www.google.com/travel/flights?hl=tr&curr=TRY&gl=TR&q=IST%20to%20MAD%202026-08-21%202026-08-24",
      "scraped_at": "2026-05-09T21:54:03.083484",
      "data_source": "url_html"
    },
    {
      "route": "IST-FRA",
      "origin": "IST",
      "dest": "FRA",
      "depart_date": "2026-06-05",
      "return_date": "2026-06-08",
      "price": 8000.0,
      "airline": "Çeşitli",
      "target": 2700,
      "alarm_threshold": 1350,
      "savings_pct": -196,
      "is_below_target": false,
      "is_mistake_fare": true,
      "has_stopover": true,
      "google_link": "https://www.google.com/travel/flights?hl=tr&curr=TRY&gl=TR&q=IST%20to%20FRA%202026-06-05%202026-06-08",
      "scraped_at": "2026-05-09T21:55:17.776328",
      "data_source": "url_html"
    },
    {
      "route": "IST-MUC",
      "origin": "IST",
      "dest": "MUC",
      "depart_date": "2026-06-05",
      "return_date": "2026-06-08",
      "price": 8000.0,
      "airline": "Çeşitli",
      "target": 2500,
      "alarm_threshold": 1250,
      "savings_pct": -220,
      "is_below_target": false,
      "is_mistake_fare": true,
      "has_stopover": true,
      "google_link": "https://www.google.com/travel/flights?hl=tr&curr=TRY&gl=TR&q=IST%20to%20MUC%202026-06-05%202026-06-08",
      "scraped_at": "2026-05-09T21:56:57.737385",
      "data_source": "url_html"
    },
    {
      "route": "IST-VIE",
      "origin": "IST",
      "dest": "VIE",
      "depart_date": "2026-08-21",
      "return_date": "2026-08-24",
      "price": 8000.0,
      "airline": "Çeşitli",
      "target": 2400,
      "alarm_threshold": 1200,
      "savings_pct": -233,
      "is_below_target": false,
      "is_mistake_fare": true,
      "has_stopover": true,
      "google_link": "https://www.google.com/travel/flights?hl=tr&curr=TRY&gl=TR&q=IST%20to%20VIE%202026-08-21%202026-08-24",
      "scraped_at": "2026-05-09T21:57:57.742340",
      "data_source": "url_html"
    },
    {
      "route": "IST-DXB",
      "origin": "IST",
      "dest": "DXB",
      "depart_date": "2026-08-21",
      "return_date": "2026-08-24",
      "price": 8000.0,
      "airline": "Çeşitli",
      "target": 2200,
      "alarm_threshold": 1100,
      "savings_pct": -264,
      "is_below_target": false,
      "is_mistake_fare": true,
      "has_stopover": true,
      "google_link": "https://www.google.com/travel/flights?hl=tr&curr=TRY&gl=TR&q=IST%20to%20DXB%202026-08-21%202026-08-24",
      "scraped_at": "2026-05-09T22:00:53.393761",
      "data_source": "url_html"
    },
    {
      "route": "IST-JFK",
      "origin": "IST",
      "dest": "JFK",
      "depart_date": "2026-06-05",
      "return_date": "2026-06-08",
      "price": 8000.0,
      "airline": "Çeşitli",
      "target": 18000,
      "alarm_threshold": 9000,
      "savings_pct": 56,
      "is_below_target": false,
      "is_mistake_fare": true,
      "has_stopover": true,
      "google_link": "https://www.google.com/travel/flights?hl=tr&curr=TRY&gl=TR&q=IST%20to%20JFK%202026-06-05%202026-06-08",
      "scraped_at": "2026-05-09T22:02:01.888887",
      "data_source": "url_html"
    },
    {
      "route": "IST-LAX",
      "origin": "IST",
      "dest": "LAX",
      "depart_date": "2026-08-07",
      "return_date": "2026-08-10",
      "price": 8000.0,
      "airline": "Çeşitli",
      "target": 20000,
      "alarm_threshold": 10000,
      "savings_pct": 60,
      "is_below_target": false,
      "is_mistake_fare": true,
      "has_stopover": true,
      "google_link": "https://www.google.com/travel/flights?hl=tr&curr=TRY&gl=TR&q=IST%20to%20LAX%202026-08-07%202026-08-10",
      "scraped_at": "2026-05-09T22:02:44.434044",
      "data_source": "url_html"
    },
    {
      "route": "SAW-CDG",
      "origin": "SAW",
      "dest": "CDG",
      "depart_date": "2026-09-04",
      "return_date": "2026-09-07",
      "price": 8000.0,
      "airline": "Çeşitli",
      "target": 2800,
      "alarm_threshold": 1400,
      "savings_pct": -186,
      "is_below_target": false,
      "is_mistake_fare": true,
      "has_stopover": true,
      "google_link": "https://www.google.com/travel/flights?hl=tr&curr=TRY&gl=TR&q=SAW%20to%20CDG%202026-09-04%202026-09-07",
      "scraped_at": "2026-05-09T22:03:42.368844",
      "data_source": "url_html"
    },
    {
      "route": "SAW-LHR",
      "origin": "SAW",
      "dest": "LHR",
      "depart_date": "2026-07-24",
      "return_date": "2026-07-27",
      "price": 8000.0,
      "airline": "Çeşitli",
      "target": 3000,
      "alarm_threshold": 1500,
      "savings_pct": -167,
      "is_below_target": false,
      "is_mistake_fare": true,
      "has_stopover": true,
      "google_link": "https://www.google.com/travel/flights?hl=tr&curr=TRY&gl=TR&q=SAW%20to%20LHR%202026-07-24%202026-07-27",
      "scraped_at": "2026-05-09T22:04:36.406096",
      "data_source": "url_html"
    },
    {
      "route": "SAW-LHR",
      "origin": "SAW",
      "dest": "LHR",
      "depart_date": "2026-06-19",
      "return_date": "2026-06-22",
      "price": 8000.0,
      "airline": "Çeşitli",
      "target": 3000,
      "alarm_threshold": 1500,
      "savings_pct": -167,
      "is_below_target": false,
      "is_mistake_fare": true,
      "has_stopover": true,
      "google_link": "https://www.google.com/travel/flights?hl=tr&curr=TRY&gl=TR&q=SAW%20to%20LHR%202026-06-19%202026-06-22",
      "scraped_at": "2026-05-09T22:05:09.595973",
      "data_source": "url_html"
    },
    {
      "route": "SAW-AMS",
      "origin": "SAW",
      "dest": "AMS",
      "depart_date": "2026-08-07",
      "return_date": "2026-08-10",
      "price": 8000.0,
      "airline": "Çeşitli",
      "target": 2600,
      "alarm_threshold": 1300,
      "savings_pct": -208,
      "is_below_target": false,
      "is_mistake_fare": true,
      "has_stopover": true,
      "google_link": "https://www.google.com/travel/flights?hl=tr&curr=TRY&gl=TR&q=SAW%20to%20AMS%202026-08-07%202026-08-10",
      "scraped_at": "2026-05-09T22:05:52.918076",
      "data_source": "url_html"
    },
    {
      "route": "SAW-AMS",
      "origin": "SAW",
      "dest": "AMS",
      "depart_date": "2026-08-21",
      "return_date": "2026-08-24",
      "price": 8000.0,
      "airline": "Çeşitli",
      "target": 2600,
      "alarm_threshold": 1300,
      "savings_pct": -208,
      "is_below_target": false,
      "is_mistake_fare": true,
      "has_stopover": true,
      "google_link": "https://www.google.com/travel/flights?hl=tr&curr=TRY&gl=TR&q=SAW%20to%20AMS%202026-08-21%202026-08-24",
      "scraped_at": "2026-05-09T22:06:24.820901",
      "data_source": "url_html"
    },
    {
      "route": "SAW-BCN",
      "origin": "SAW",
      "dest": "BCN",
      "depart_date": "2026-09-04",
      "return_date": "2026-09-07",
      "price": 8000.0,
      "airline": "Çeşitli",
      "target": 2700,
      "alarm_threshold": 1350,
      "savings_pct": -196,
      "is_below_target": false,
      "is_mistake_fare": true,
      "has_stopover": true,
      "google_link": "https://www.google.com/travel/flights?hl=tr&curr=TRY&gl=TR&q=SAW%20to%20BCN%202026-09-04%202026-09-07",
      "scraped_at": "2026-05-09T22:06:50.517718",
      "data_source": "url_html"
    },
    {
      "route": "SAW-FCO",
      "origin": "SAW",
      "dest": "FCO",
      "depart_date": "2026-08-07",
      "return_date": "2026-08-10",
      "price": 8000.0,
      "airline": "Çeşitli",
      "target": 2400,
      "alarm_threshold": 1200,
      "savings_pct": -233,
      "is_below_target": false,
      "is_mistake_fare": true,
      "has_stopover": true,
      "google_link": "https://www.google.com/travel/flights?hl=tr&curr=TRY&gl=TR&q=SAW%20to%20FCO%202026-08-07%202026-08-10",
      "scraped_at": "2026-05-09T22:07:58.293815",
      "data_source": "url_html"
    },
    {
      "route": "IST-MUC",
      "origin": "IST",
      "dest": "MUC",
      "depart_date": "2026-06-19",
      "return_date": "2026-06-22",
      "price": 8607.0,
      "airline": "Çeşitli",
      "target": 2500,
      "alarm_threshold": 1250,
      "savings_pct": -244,
      "is_below_target": false,
      "is_mistake_fare": false,
      "has_stopover": false,
      "google_link": "https://www.google.com/travel/flights?hl=tr&curr=TRY&gl=TR&q=IST%20to%20MUC%202026-06-19%202026-06-22",
      "scraped_at": "2026-05-09T21:56:15.768797",
      "data_source": "playwright_dom"
    },
    {
      "route": "IST-ATH",
      "origin": "IST",
      "dest": "ATH",
      "depart_date": "2026-05-29",
      "return_date": "2026-06-01",
      "price": 8889.0,
      "airline": "Çeşitli",
      "target": 1800,
      "alarm_threshold": 900,
      "savings_pct": -394,
      "is_below_target": false,
      "is_mistake_fare": false,
      "has_stopover": false,
      "google_link": "https://www.google.com/travel/flights?hl=tr&curr=TRY&gl=TR&q=IST%20to%20ATH%202026-05-29%202026-06-01",
      "scraped_at": "2026-05-09T21:59:27.828119",
      "data_source": "playwright_dom"
    },
    {
      "route": "SAW-LHR",
      "origin": "SAW",
      "dest": "LHR",
      "depart_date": "2026-06-19",
      "return_date": "2026-06-22",
      "price": 8922.0,
      "airline": "Çeşitli",
      "target": 3000,
      "alarm_threshold": 1500,
      "savings_pct": -197,
      "is_below_target": false,
      "is_mistake_fare": true,
      "has_stopover": true,
      "google_link": "https://www.google.com/travel/flights?hl=tr&curr=TRY&gl=TR&q=SAW%20to%20LHR%202026-06-19%202026-06-22",
      "scraped_at": "2026-05-09T22:05:09.595973",
      "data_source": "url_html"
    },
    {
      "route": "IST-ATH",
      "origin": "IST",
      "dest": "ATH",
      "depart_date": "2026-09-04",
      "return_date": "2026-09-07",
      "price": 9288.0,
      "airline": "Çeşitli",
      "target": 1800,
      "alarm_threshold": 900,
      "savings_pct": -416,
      "is_below_target": false,
      "is_mistake_fare": false,
      "has_stopover": false,
      "google_link": "https://www.google.com/travel/flights?hl=tr&curr=TRY&gl=TR&q=IST%20to%20ATH%202026-09-04%202026-09-07",
      "scraped_at": "2026-05-09T21:59:59.034509",
      "data_source": "playwright_dom"
    },
    {
      "route": "IST-PRG",
      "origin": "IST",
      "dest": "PRG",
      "depart_date": "2026-06-26",
      "return_date": "2026-06-29",
      "price": 9537.0,
      "airline": "Çeşitli",
      "target": 2600,
      "alarm_threshold": 1300,
      "savings_pct": -267,
      "is_below_target": false,
      "is_mistake_fare": false,
      "has_stopover": false,
      "google_link": "https://www.google.com/travel/flights?hl=tr&curr=TRY&gl=TR&q=IST%20to%20PRG%202026-06-26%202026-06-29",
      "scraped_at": "2026-05-09T21:58:23.846827",
      "data_source": "playwright_dom"
    },
    {
      "route": "IST-PRG",
      "origin": "IST",
      "dest": "PRG",
      "depart_date": "2026-06-26",
      "return_date": "2026-06-29",
      "price": 9808.0,
      "airline": "Çeşitli",
      "target": 2600,
      "alarm_threshold": 1300,
      "savings_pct": -277,
      "is_below_target": false,
      "is_mistake_fare": false,
      "has_stopover": false,
      "google_link": "https://www.google.com/travel/flights?hl=tr&curr=TRY&gl=TR&q=IST%20to%20PRG%202026-06-26%202026-06-29",
      "scraped_at": "2026-05-09T21:58:23.846827",
      "data_source": "playwright_dom"
    },
    {
      "route": "IST-MUC",
      "origin": "IST",
      "dest": "MUC",
      "depart_date": "2026-06-19",
      "return_date": "2026-06-22",
      "price": 10214.0,
      "airline": "Çeşitli",
      "target": 2500,
      "alarm_threshold": 1250,
      "savings_pct": -309,
      "is_below_target": false,
      "is_mistake_fare": false,
      "has_stopover": false,
      "google_link": "https://www.google.com/travel/flights?hl=tr&curr=TRY&gl=TR&q=IST%20to%20MUC%202026-06-19%202026-06-22",
      "scraped_at": "2026-05-09T21:56:15.768797",
      "data_source": "playwright_dom"
    },
    {
      "route": "IST-MUC",
      "origin": "IST",
      "dest": "MUC",
      "depart_date": "2026-06-19",
      "return_date": "2026-06-22",
      "price": 10350.0,
      "airline": "Çeşitli",
      "target": 2500,
      "alarm_threshold": 1250,
      "savings_pct": -314,
      "is_below_target": false,
      "is_mistake_fare": false,
      "has_stopover": false,
      "google_link": "https://www.google.com/travel/flights?hl=tr&curr=TRY&gl=TR&q=IST%20to%20MUC%202026-06-19%202026-06-22",
      "scraped_at": "2026-05-09T21:56:15.768797",
      "data_source": "playwright_dom"
    },
    {
      "route": "IST-VIE",
      "origin": "IST",
      "dest": "VIE",
      "depart_date": "2026-06-26",
      "return_date": "2026-06-29",
      "price": 10359.0,
      "airline": "Çeşitli",
      "target": 2400,
      "alarm_threshold": 1200,
      "savings_pct": -332,
      "is_below_target": false,
      "is_mistake_fare": false,
      "has_stopover": false,
      "google_link": "https://www.google.com/travel/flights?hl=tr&curr=TRY&gl=TR&q=IST%20to%20VIE%202026-06-26%202026-06-29",
      "scraped_at": "2026-05-09T21:57:25.805143",
      "data_source": "playwright_dom"
    },
    {
      "route": "IST-VIE",
      "origin": "IST",
      "dest": "VIE",
      "depart_date": "2026-06-26",
      "return_date": "2026-06-29",
      "price": 10495.0,
      "airline": "Çeşitli",
      "target": 2400,
      "alarm_threshold": 1200,
      "savings_pct": -337,
      "is_below_target": false,
      "is_mistake_fare": false,
      "has_stopover": false,
      "google_link": "https://www.google.com/travel/flights?hl=tr&curr=TRY&gl=TR&q=IST%20to%20VIE%202026-06-26%202026-06-29",
      "scraped_at": "2026-05-09T21:57:25.805143",
      "data_source": "playwright_dom"
    },
    {
      "route": "IST-PRG",
      "origin": "IST",
      "dest": "PRG",
      "depart_date": "2026-06-26",
      "return_date": "2026-06-29",
      "price": 10580.0,
      "airline": "Çeşitli",
      "target": 2600,
      "alarm_threshold": 1300,
      "savings_pct": -307,
      "is_below_target": false,
      "is_mistake_fare": false,
      "has_stopover": false,
      "google_link": "https://www.google.com/travel/flights?hl=tr&curr=TRY&gl=TR&q=IST%20to%20PRG%202026-06-26%202026-06-29",
      "scraped_at": "2026-05-09T21:58:23.846827",
      "data_source": "playwright_dom"
    },
    {
      "route": "IST-PRG",
      "origin": "IST",
      "dest": "PRG",
      "depart_date": "2026-06-26",
      "return_date": "2026-06-29",
      "price": 11080.0,
      "airline": "Çeşitli",
      "target": 2600,
      "alarm_threshold": 1300,
      "savings_pct": -326,
      "is_below_target": false,
      "is_mistake_fare": false,
      "has_stopover": false,
      "google_link": "https://www.google.com/travel/flights?hl=tr&curr=TRY&gl=TR&q=IST%20to%20PRG%202026-06-26%202026-06-29",
      "scraped_at": "2026-05-09T21:58:23.846827",
      "data_source": "playwright_dom"
    },
    {
      "route": "IST-VIE",
      "origin": "IST",
      "dest": "VIE",
      "depart_date": "2026-06-26",
      "return_date": "2026-06-29",
      "price": 11083.0,
      "airline": "Çeşitli",
      "target": 2400,
      "alarm_threshold": 1200,
      "savings_pct": -362,
      "is_below_target": false,
      "is_mistake_fare": false,
      "has_stopover": false,
      "google_link": "https://www.google.com/travel/flights?hl=tr&curr=TRY&gl=TR&q=IST%20to%20VIE%202026-06-26%202026-06-29",
      "scraped_at": "2026-05-09T21:57:25.805143",
      "data_source": "playwright_dom"
    },
    {
      "route": "IST-PRG",
      "origin": "IST",
      "dest": "PRG",
      "depart_date": "2026-07-24",
      "return_date": "2026-07-27",
      "price": 11110.0,
      "airline": "Çeşitli",
      "target": 2600,
      "alarm_threshold": 1300,
      "savings_pct": -327,
      "is_below_target": false,
      "is_mistake_fare": false,
      "has_stopover": false,
      "google_link": "https://www.google.com/travel/flights?hl=tr&curr=TRY&gl=TR&q=IST%20to%20PRG%202026-07-24%202026-07-27",
      "scraped_at": "2026-05-09T21:58:56.621446",
      "data_source": "playwright_dom"
    },
    {
      "route": "IST-MUC",
      "origin": "IST",
      "dest": "MUC",
      "depart_date": "2026-06-19",
      "return_date": "2026-06-22",
      "price": 11179.0,
      "airline": "Çeşitli",
      "target": 2500,
      "alarm_threshold": 1250,
      "savings_pct": -347,
      "is_below_target": false,
      "is_mistake_fare": false,
      "has_stopover": false,
      "google_link": "https://www.google.com/travel/flights?hl=tr&curr=TRY&gl=TR&q=IST%20to%20MUC%202026-06-19%202026-06-22",
      "scraped_at": "2026-05-09T21:56:15.768797",
      "data_source": "playwright_dom"
    },
    {
      "route": "IST-LHR",
      "origin": "IST",
      "dest": "LHR",
      "depart_date": "2026-08-21",
      "return_date": "2026-08-24",
      "price": 11226.0,
      "airline": "Çeşitli",
      "target": 3200,
      "alarm_threshold": 1600,
      "savings_pct": -251,
      "is_below_target": false,
      "is_mistake_fare": true,
      "has_stopover": true,
      "google_link": "https://www.google.com/travel/flights?hl=tr&curr=TRY&gl=TR&q=IST%20to%20LHR%202026-08-21%202026-08-24",
      "scraped_at": "2026-05-09T21:50:32.996602",
      "data_source": "url_html"
    },
    {
      "route": "IST-VIE",
      "origin": "IST",
      "dest": "VIE",
      "depart_date": "2026-06-26",
      "return_date": "2026-06-29",
      "price": 11265.0,
      "airline": "Çeşitli",
      "target": 2400,
      "alarm_threshold": 1200,
      "savings_pct": -369,
      "is_below_target": false,
      "is_mistake_fare": false,
      "has_stopover": false,
      "google_link": "https://www.google.com/travel/flights?hl=tr&curr=TRY&gl=TR&q=IST%20to%20VIE%202026-06-26%202026-06-29",
      "scraped_at": "2026-05-09T21:57:25.805143",
      "data_source": "playwright_dom"
    },
    {
      "route": "IST-BCN",
      "origin": "IST",
      "dest": "BCN",
      "depart_date": "2026-06-26",
      "return_date": "2026-06-29",
      "price": 11442.0,
      "airline": "Çeşitli",
      "target": 2900,
      "alarm_threshold": 1450,
      "savings_pct": -295,
      "is_below_target": false,
      "is_mistake_fare": false,
      "has_stopover": false,
      "google_link": "https://www.google.com/travel/flights?hl=tr&curr=TRY&gl=TR&q=IST%20to%20BCN%202026-06-26%202026-06-29",
      "scraped_at": "2026-05-09T21:52:09.061477",
      "data_source": "playwright_dom"
    },
    {
      "route": "IST-FRA",
      "origin": "IST",
      "dest": "FRA",
      "depart_date": "2026-05-29",
      "return_date": "2026-06-01",
      "price": 11745.0,
      "airline": "Çeşitli",
      "target": 2700,
      "alarm_threshold": 1350,
      "savings_pct": -335,
      "is_below_target": false,
      "is_mistake_fare": false,
      "has_stopover": false,
      "google_link": "https://www.google.com/travel/flights?hl=tr&curr=TRY&gl=TR&q=IST%20to%20FRA%202026-05-29%202026-06-01",
      "scraped_at": "2026-05-09T21:55:46.559023",
      "data_source": "playwright_dom"
    },
    {
      "route": "IST-MUC",
      "origin": "IST",
      "dest": "MUC",
      "depart_date": "2026-06-19",
      "return_date": "2026-06-22",
      "price": 11799.0,
      "airline": "Çeşitli",
      "target": 2500,
      "alarm_threshold": 1250,
      "savings_pct": -372,
      "is_below_target": false,
      "is_mistake_fare": false,
      "has_stopover": false,
      "google_link": "https://www.google.com/travel/flights?hl=tr&curr=TRY&gl=TR&q=IST%20to%20MUC%202026-06-19%202026-06-22",
      "scraped_at": "2026-05-09T21:56:15.768797",
      "data_source": "playwright_dom"
    },
    {
      "route": "IST-BCN",
      "origin": "IST",
      "dest": "BCN",
      "depart_date": "2026-06-26",
      "return_date": "2026-06-29",
      "price": 11895.0,
      "airline": "Çeşitli",
      "target": 2900,
      "alarm_threshold": 1450,
      "savings_pct": -310,
      "is_below_target": false,
      "is_mistake_fare": false,
      "has_stopover": false,
      "google_link": "https://www.google.com/travel/flights?hl=tr&curr=TRY&gl=TR&q=IST%20to%20BCN%202026-06-26%202026-06-29",
      "scraped_at": "2026-05-09T21:52:09.061477",
      "data_source": "playwright_dom"
    },
    {
      "route": "IST-VIE",
      "origin": "IST",
      "dest": "VIE",
      "depart_date": "2026-06-26",
      "return_date": "2026-06-29",
      "price": 11943.0,
      "airline": "Çeşitli",
      "target": 2400,
      "alarm_threshold": 1200,
      "savings_pct": -398,
      "is_below_target": false,
      "is_mistake_fare": false,
      "has_stopover": false,
      "google_link": "https://www.google.com/travel/flights?hl=tr&curr=TRY&gl=TR&q=IST%20to%20VIE%202026-06-26%202026-06-29",
      "scraped_at": "2026-05-09T21:57:25.805143",
      "data_source": "playwright_dom"
    },
    {
      "route": "IST-FCO",
      "origin": "IST",
      "dest": "FCO",
      "depart_date": "2026-05-29",
      "return_date": "2026-06-01",
      "price": 12031.0,
      "airline": "Çeşitli",
      "target": 2600,
      "alarm_threshold": 1300,
      "savings_pct": -363,
      "is_below_target": false,
      "is_mistake_fare": false,
      "has_stopover": false,
      "google_link": "https://www.google.com/travel/flights?hl=tr&curr=TRY&gl=TR&q=IST%20to%20FCO%202026-05-29%202026-06-01",
      "scraped_at": "2026-05-09T21:53:03.124365",
      "data_source": "playwright_dom"
    },
    {
      "route": "SAW-BCN",
      "origin": "SAW",
      "dest": "BCN",
      "depart_date": "2026-09-04",
      "return_date": "2026-09-07",
      "price": 12054.0,
      "airline": "Çeşitli",
      "target": 2700,
      "alarm_threshold": 1350,
      "savings_pct": -346,
      "is_below_target": false,
      "is_mistake_fare": true,
      "has_stopover": true,
      "google_link": "https://www.google.com/travel/flights?hl=tr&curr=TRY&gl=TR&q=SAW%20to%20BCN%202026-09-04%202026-09-07",
      "scraped_at": "2026-05-09T22:06:50.517718",
      "data_source": "url_html"
    },
    {
      "route": "IST-FCO",
      "origin": "IST",
      "dest": "FCO",
      "depart_date": "2026-05-29",
      "return_date": "2026-06-01",
      "price": 12294.0,
      "airline": "Çeşitli",
      "target": 2600,
      "alarm_threshold": 1300,
      "savings_pct": -373,
      "is_below_target": false,
      "is_mistake_fare": false,
      "has_stopover": false,
      "google_link": "https://www.google.com/travel/flights?hl=tr&curr=TRY&gl=TR&q=IST%20to%20FCO%202026-05-29%202026-06-01",
      "scraped_at": "2026-05-09T21:53:03.124365",
      "data_source": "playwright_dom"
    },
    {
      "route": "IST-PRG",
      "origin": "IST",
      "dest": "PRG",
      "depart_date": "2026-07-24",
      "return_date": "2026-07-27",
      "price": 12434.0,
      "airline": "Çeşitli",
      "target": 2600,
      "alarm_threshold": 1300,
      "savings_pct": -378,
      "is_below_target": false,
      "is_mistake_fare": false,
      "has_stopover": false,
      "google_link": "https://www.google.com/travel/flights?hl=tr&curr=TRY&gl=TR&q=IST%20to%20PRG%202026-07-24%202026-07-27",
      "scraped_at": "2026-05-09T21:58:56.621446",
      "data_source": "playwright_dom"
    },
    {
      "route": "IST-BCN",
      "origin": "IST",
      "dest": "BCN",
      "depart_date": "2026-06-26",
      "return_date": "2026-06-29",
      "price": 12506.0,
      "airline": "Çeşitli",
      "target": 2900,
      "alarm_threshold": 1450,
      "savings_pct": -331,
      "is_below_target": false,
      "is_mistake_fare": false,
      "has_stopover": false,
      "google_link": "https://www.google.com/travel/flights?hl=tr&curr=TRY&gl=TR&q=IST%20to%20BCN%202026-06-26%202026-06-29",
      "scraped_at": "2026-05-09T21:52:09.061477",
      "data_source": "playwright_dom"
    },
    {
      "route": "IST-FCO",
      "origin": "IST",
      "dest": "FCO",
      "depart_date": "2026-05-29",
      "return_date": "2026-06-01",
      "price": 12788.0,
      "airline": "Çeşitli",
      "target": 2600,
      "alarm_threshold": 1300,
      "savings_pct": -392,
      "is_below_target": false,
      "is_mistake_fare": false,
      "has_stopover": false,
      "google_link": "https://www.google.com/travel/flights?hl=tr&curr=TRY&gl=TR&q=IST%20to%20FCO%202026-05-29%202026-06-01",
      "scraped_at": "2026-05-09T21:53:03.124365",
      "data_source": "playwright_dom"
    },
    {
      "route": "IST-MAD",
      "origin": "IST",
      "dest": "MAD",
      "depart_date": "2026-05-29",
      "return_date": "2026-06-01",
      "price": 12849.0,
      "airline": "Çeşitli",
      "target": 3100,
      "alarm_threshold": 1550,
      "savings_pct": -314,
      "is_below_target": false,
      "is_mistake_fare": false,
      "has_stopover": false,
      "google_link": "https://www.google.com/travel/flights?hl=tr&curr=TRY&gl=TR&q=IST%20to%20MAD%202026-05-29%202026-06-01",
      "scraped_at": "2026-05-09T21:54:33.587803",
      "data_source": "playwright_dom"
    },
    {
      "route": "IST-FRA",
      "origin": "IST",
      "dest": "FRA",
      "depart_date": "2026-05-29",
      "return_date": "2026-06-01",
      "price": 12867.0,
      "airline": "Çeşitli",
      "target": 2700,
      "alarm_threshold": 1350,
      "savings_pct": -377,
      "is_below_target": false,
      "is_mistake_fare": false,
      "has_stopover": false,
      "google_link": "https://www.google.com/travel/flights?hl=tr&curr=TRY&gl=TR&q=IST%20to%20FRA%202026-05-29%202026-06-01",
      "scraped_at": "2026-05-09T21:55:46.559023",
      "data_source": "playwright_dom"
    },
    {
      "route": "IST-CDG",
      "origin": "IST",
      "dest": "CDG",
      "depart_date": "2026-09-04",
      "return_date": "2026-09-07",
      "price": 13041.0,
      "airline": "Çeşitli",
      "target": 3000,
      "alarm_threshold": 1500,
      "savings_pct": -335,
      "is_below_target": false,
      "is_mistake_fare": false,
      "has_stopover": false,
      "google_link": "https://www.google.com/travel/flights?hl=tr&curr=TRY&gl=TR&q=IST%20to%20CDG%202026-09-04%202026-09-07",
      "scraped_at": "2026-05-09T21:48:54.635067",
      "data_source": "playwright_dom"
    },
    {
      "route": "SAW-CDG",
      "origin": "SAW",
      "dest": "CDG",
      "depart_date": "2026-09-04",
      "return_date": "2026-09-07",
      "price": 13041.0,
      "airline": "Çeşitli",
      "target": 2800,
      "alarm_threshold": 1400,
      "savings_pct": -366,
      "is_below_target": false,
      "is_mistake_fare": true,
      "has_stopover": true,
      "google_link": "https://www.google.com/travel/flights?hl=tr&curr=TRY&gl=TR&q=SAW%20to%20CDG%202026-09-04%202026-09-07",
      "scraped_at": "2026-05-09T22:03:42.368844",
      "data_source": "url_html"
    },
    {
      "route": "IST-AMS",
      "origin": "IST",
      "dest": "AMS",
      "depart_date": "2026-06-26",
      "return_date": "2026-06-29",
      "price": 13240.0,
      "airline": "Çeşitli",
      "target": 2800,
      "alarm_threshold": 1400,
      "savings_pct": -373,
      "is_below_target": false,
      "is_mistake_fare": false,
      "has_stopover": false,
      "google_link": "https://www.google.com/travel/flights?hl=tr&curr=TRY&gl=TR&q=IST%20to%20AMS%202026-06-26%202026-06-29",
      "scraped_at": "2026-05-09T21:50:59.993191",
      "data_source": "playwright_dom"
    },
    {
      "route": "IST-CDG",
      "origin": "IST",
      "dest": "CDG",
      "depart_date": "2026-06-26",
      "return_date": "2026-06-29",
      "price": 13496.0,
      "airline": "Çeşitli",
      "target": 3000,
      "alarm_threshold": 1500,
      "savings_pct": -350,
      "is_below_target": false,
      "is_mistake_fare": false,
      "has_stopover": false,
      "google_link": "https://www.google.com/travel/flights?hl=tr&curr=TRY&gl=TR&q=IST%20to%20CDG%202026-06-26%202026-06-29",
      "scraped_at": "2026-05-09T21:49:21.638546",
      "data_source": "playwright_dom"
    },
    {
      "route": "SAW-CDG",
      "origin": "SAW",
      "dest": "CDG",
      "depart_date": "2026-06-19",
      "return_date": "2026-06-22",
      "price": 13668.0,
      "airline": "Çeşitli",
      "target": 2800,
      "alarm_threshold": 1400,
      "savings_pct": -388,
      "is_below_target": false,
      "is_mistake_fare": false,
      "has_stopover": false,
      "google_link": "https://www.google.com/travel/flights?hl=tr&curr=TRY&gl=TR&q=SAW%20to%20CDG%202026-06-19%202026-06-22",
      "scraped_at": "2026-05-09T22:04:09.156517",
      "data_source": "playwright_dom"
    },
    {
      "route": "IST-AMS",
      "origin": "IST",
      "dest": "AMS",
      "depart_date": "2026-06-26",
      "return_date": "2026-06-29",
      "price": 13918.0,
      "airline": "Çeşitli",
      "target": 2800,
      "alarm_threshold": 1400,
      "savings_pct": -397,
      "is_below_target": false,
      "is_mistake_fare": false,
      "has_stopover": false,
      "google_link": "https://www.google.com/travel/flights?hl=tr&curr=TRY&gl=TR&q=IST%20to%20AMS%202026-06-26%202026-06-29",
      "scraped_at": "2026-05-09T21:50:59.993191",
      "data_source": "playwright_dom"
    },
    {
      "route": "IST-CDG",
      "origin": "IST",
      "dest": "CDG",
      "depart_date": "2026-06-26",
      "return_date": "2026-06-29",
      "price": 13993.0,
      "airline": "Çeşitli",
      "target": 3000,
      "alarm_threshold": 1500,
      "savings_pct": -366,
      "is_below_target": false,
      "is_mistake_fare": false,
      "has_stopover": false,
      "google_link": "https://www.google.com/travel/flights?hl=tr&curr=TRY&gl=TR&q=IST%20to%20CDG%202026-06-26%202026-06-29",
      "scraped_at": "2026-05-09T21:49:21.638546",
      "data_source": "playwright_dom"
    },
    {
      "route": "IST-CDG",
      "origin": "IST",
      "dest": "CDG",
      "depart_date": "2026-09-04",
      "return_date": "2026-09-07",
      "price": 14171.0,
      "airline": "Çeşitli",
      "target": 3000,
      "alarm_threshold": 1500,
      "savings_pct": -372,
      "is_below_target": false,
      "is_mistake_fare": false,
      "has_stopover": false,
      "google_link": "https://www.google.com/travel/flights?hl=tr&curr=TRY&gl=TR&q=IST%20to%20CDG%202026-09-04%202026-09-07",
      "scraped_at": "2026-05-09T21:48:54.635067",
      "data_source": "playwright_dom"
    },
    {
      "route": "IST-CDG",
      "origin": "IST",
      "dest": "CDG",
      "depart_date": "2026-09-04",
      "return_date": "2026-09-07",
      "price": 14439.0,
      "airline": "Çeşitli",
      "target": 3000,
      "alarm_threshold": 1500,
      "savings_pct": -381,
      "is_below_target": false,
      "is_mistake_fare": false,
      "has_stopover": false,
      "google_link": "https://www.google.com/travel/flights?hl=tr&curr=TRY&gl=TR&q=IST%20to%20CDG%202026-09-04%202026-09-07",
      "scraped_at": "2026-05-09T21:48:54.635067",
      "data_source": "playwright_dom"
    },
    {
      "route": "IST-MAD",
      "origin": "IST",
      "dest": "MAD",
      "depart_date": "2026-05-29",
      "return_date": "2026-06-01",
      "price": 14568.0,
      "airline": "Çeşitli",
      "target": 3100,
      "alarm_threshold": 1550,
      "savings_pct": -370,
      "is_below_target": false,
      "is_mistake_fare": false,
      "has_stopover": false,
      "google_link": "https://www.google.com/travel/flights?hl=tr&curr=TRY&gl=TR&q=IST%20to%20MAD%202026-05-29%202026-06-01",
      "scraped_at": "2026-05-09T21:54:33.587803",
      "data_source": "playwright_dom"
    },
    {
      "route": "IST-MAD",
      "origin": "IST",
      "dest": "MAD",
      "depart_date": "2026-05-29",
      "return_date": "2026-06-01",
      "price": 14616.0,
      "airline": "Çeşitli",
      "target": 3100,
      "alarm_threshold": 1550,
      "savings_pct": -371,
      "is_below_target": false,
      "is_mistake_fare": false,
      "has_stopover": false,
      "google_link": "https://www.google.com/travel/flights?hl=tr&curr=TRY&gl=TR&q=IST%20to%20MAD%202026-05-29%202026-06-01",
      "scraped_at": "2026-05-09T21:54:33.587803",
      "data_source": "playwright_dom"
    },
    {
      "route": "IST-CDG",
      "origin": "IST",
      "dest": "CDG",
      "depart_date": "2026-06-26",
      "return_date": "2026-06-29",
      "price": 14933.0,
      "airline": "Çeşitli",
      "target": 3000,
      "alarm_threshold": 1500,
      "savings_pct": -398,
      "is_below_target": false,
      "is_mistake_fare": false,
      "has_stopover": false,
      "google_link": "https://www.google.com/travel/flights?hl=tr&curr=TRY&gl=TR&q=IST%20to%20CDG%202026-06-26%202026-06-29",
      "scraped_at": "2026-05-09T21:49:21.638546",
      "data_source": "playwright_dom"
    },
    {
      "route": "SAW-LHR",
      "origin": "SAW",
      "dest": "LHR",
      "depart_date": "2026-07-24",
      "return_date": "2026-07-27",
      "price": 15697.0,
      "airline": "Çeşitli",
      "target": 3000,
      "alarm_threshold": 1500,
      "savings_pct": -423,
      "is_below_target": false,
      "is_mistake_fare": true,
      "has_stopover": true,
      "google_link": "https://www.google.com/travel/flights?hl=tr&curr=TRY&gl=TR&q=SAW%20to%20LHR%202026-07-24%202026-07-27",
      "scraped_at": "2026-05-09T22:04:36.406096",
      "data_source": "url_html"
    },
    {
      "route": "IST-JFK",
      "origin": "IST",
      "dest": "JFK",
      "depart_date": "2026-06-05",
      "return_date": "2026-06-08",
      "price": 30001.0,
      "airline": "Çeşitli",
      "target": 18000,
      "alarm_threshold": 9000,
      "savings_pct": -67,
      "is_below_target": false,
      "is_mistake_fare": true,
      "has_stopover": true,
      "google_link": "https://www.google.com/travel/flights?hl=tr&curr=TRY&gl=TR&q=IST%20to%20JFK%202026-06-05%202026-06-08",
      "scraped_at": "2026-05-09T22:02:01.888887",
      "data_source": "url_html"
    },
    {
      "route": "IST-LAX",
      "origin": "IST",
      "dest": "LAX",
      "depart_date": "2026-08-07",
      "return_date": "2026-08-10",
      "price": 30001.0,
      "airline": "Çeşitli",
      "target": 20000,
      "alarm_threshold": 10000,
      "savings_pct": -50,
      "is_below_target": false,
      "is_mistake_fare": true,
      "has_stopover": true,
      "google_link": "https://www.google.com/travel/flights?hl=tr&curr=TRY&gl=TR&q=IST%20to%20LAX%202026-08-07%202026-08-10",
      "scraped_at": "2026-05-09T22:02:44.434044",
      "data_source": "url_html"
    },
    {
      "route": "IST-LAX",
      "origin": "IST",
      "dest": "LAX",
      "depart_date": "2026-06-26",
      "return_date": "2026-06-29",
      "price": 33636.0,
      "airline": "Çeşitli",
      "target": 20000,
      "alarm_threshold": 10000,
      "savings_pct": -68,
      "is_below_target": false,
      "is_mistake_fare": false,
      "has_stopover": false,
      "google_link": "https://www.google.com/travel/flights?hl=tr&curr=TRY&gl=TR&q=IST%20to%20LAX%202026-06-26%202026-06-29",
      "scraped_at": "2026-05-09T22:03:13.390476",
      "data_source": "playwright_dom"
    },
    {
      "route": "IST-LAX",
      "origin": "IST",
      "dest": "LAX",
      "depart_date": "2026-06-26",
      "return_date": "2026-06-29",
      "price": 34278.0,
      "airline": "Çeşitli",
      "target": 20000,
      "alarm_threshold": 10000,
      "savings_pct": -71,
      "is_below_target": false,
      "is_mistake_fare": false,
      "has_stopover": false,
      "google_link": "https://www.google.com/travel/flights?hl=tr&curr=TRY&gl=TR&q=IST%20to%20LAX%202026-06-26%202026-06-29",
      "scraped_at": "2026-05-09T22:03:13.390476",
      "data_source": "playwright_dom"
    },
    {
      "route": "IST-JFK",
      "origin": "IST",
      "dest": "JFK",
      "depart_date": "2026-06-05",
      "return_date": "2026-06-08",
      "price": 40400.0,
      "airline": "Çeşitli",
      "target": 18000,
      "alarm_threshold": 9000,
      "savings_pct": -124,
      "is_below_target": false,
      "is_mistake_fare": true,
      "has_stopover": true,
      "google_link": "https://www.google.com/travel/flights?hl=tr&curr=TRY&gl=TR&q=IST%20to%20JFK%202026-06-05%202026-06-08",
      "scraped_at": "2026-05-09T22:02:01.888887",
      "data_source": "url_html"
    },
    {
      "route": "IST-LAX",
      "origin": "IST",
      "dest": "LAX",
      "depart_date": "2026-08-07",
      "return_date": "2026-08-10",
      "price": 40400.0,
      "airline": "Çeşitli",
      "target": 20000,
      "alarm_threshold": 10000,
      "savings_pct": -102,
      "is_below_target": false,
      "is_mistake_fare": true,
      "has_stopover": true,
      "google_link": "https://www.google.com/travel/flights?hl=tr&curr=TRY&gl=TR&q=IST%20to%20LAX%202026-08-07%202026-08-10",
      "scraped_at": "2026-05-09T22:02:44.434044",
      "data_source": "url_html"
    },
    {
      "route": "IST-LAX",
      "origin": "IST",
      "dest": "LAX",
      "depart_date": "2026-06-26",
      "return_date": "2026-06-29",
      "price": 40639.0,
      "airline": "Çeşitli",
      "target": 20000,
      "alarm_threshold": 10000,
      "savings_pct": -103,
      "is_below_target": false,
      "is_mistake_fare": false,
      "has_stopover": false,
      "google_link": "https://www.google.com/travel/flights?hl=tr&curr=TRY&gl=TR&q=IST%20to%20LAX%202026-06-26%202026-06-29",
      "scraped_at": "2026-05-09T22:03:13.390476",
      "data_source": "playwright_dom"
    },
    {
      "route": "IST-LAX",
      "origin": "IST",
      "dest": "LAX",
      "depart_date": "2026-06-26",
      "return_date": "2026-06-29",
      "price": 43579.0,
      "airline": "Çeşitli",
      "target": 20000,
      "alarm_threshold": 10000,
      "savings_pct": -118,
      "is_below_target": false,
      "is_mistake_fare": false,
      "has_stopover": false,
      "google_link": "https://www.google.com/travel/flights?hl=tr&curr=TRY&gl=TR&q=IST%20to%20LAX%202026-06-26%202026-06-29",
      "scraped_at": "2026-05-09T22:03:13.390476",
      "data_source": "playwright_dom"
    },
    {
      "route": "IST-LAX",
      "origin": "IST",
      "dest": "LAX",
      "depart_date": "2026-06-26",
      "return_date": "2026-06-29",
      "price": 56376.0,
      "airline": "Çeşitli",
      "target": 20000,
      "alarm_threshold": 10000,
      "savings_pct": -182,
      "is_below_target": false,
      "is_mistake_fare": false,
      "has_stopover": false,
      "google_link": "https://www.google.com/travel/flights?hl=tr&curr=TRY&gl=TR&q=IST%20to%20LAX%202026-06-26%202026-06-29",
      "scraped_at": "2026-05-09T22:03:13.390476",
      "data_source": "playwright_dom"
    },
    {
      "route": "IST-LAX",
      "origin": "IST",
      "dest": "LAX",
      "depart_date": "2026-08-07",
      "return_date": "2026-08-10",
      "price": 86400.0,
      "airline": "Çeşitli",
      "target": 20000,
      "alarm_threshold": 10000,
      "savings_pct": -332,
      "is_below_target": false,
      "is_mistake_fare": true,
      "has_stopover": true,
      "google_link": "https://www.google.com/travel/flights?hl=tr&curr=TRY&gl=TR&q=IST%20to%20LAX%202026-08-07%202026-08-10",
      "scraped_at": "2026-05-09T22:02:44.434044",
      "data_source": "url_html"
    }
  ]
}